<?xml version="1.0"?>
<opencv_storage>
<my_svm type_id="opencv-ml-svm">
  <svm_type>C_SVC</svm_type>
  <kernel><type>LINEAR</type></kernel>
  <C>1.0000000000000001e-01</C>
  <term_criteria><epsilon>1.1920928955078125e-07</epsilon>
    <iterations>1000</iterations></term_criteria>
  <var_all>2916</var_all>
  <var_count>2916</var_count>
  <class_count>2</class_count>
  <class_labels type_id="opencv-matrix">
    <rows>1</rows>
    <cols>2</cols>
    <dt>i</dt>
    <data>
      1 2</data></class_labels>
  <sv_total>1</sv_total>
  <support_vectors>
    <_>
      -1.79672788e-03 -7.83240888e-03 9.76473652e-03 -1.38024325e-02
      2.26185955e-02 2.53280476e-02 2.40486562e-02 1.45216109e-02
      4.75914404e-03 1.11814030e-02 -7.62604643e-03 8.55061598e-03
      -7.83336407e-04 -2.47646011e-02 -3.55362240e-03 6.73774583e-03
      1.81741565e-02 1.27595905e-02 5.17480122e-03 -1.65602453e-02
      1.36371711e-02 9.66619421e-03 3.12221125e-02 5.37283085e-02
      1.78142004e-02 4.00250545e-03 5.07632364e-03 1.78299956e-02
      3.18147317e-02 3.61075066e-02 2.70839520e-02 -3.35004814e-02
      1.17836324e-02 1.75728556e-02 3.00435536e-02 3.65575850e-02
      -8.07784498e-03 -1.27818612e-02 -2.16016993e-02 -1.32840816e-02
      -1.49546973e-02 3.17104645e-02 3.94238457e-02 3.22365277e-02
      5.68417506e-03 4.07289853e-03 5.05447341e-03 -6.12648064e-03
      4.87760920e-03 -7.32322270e-03 1.60473995e-02 2.97457352e-02
      1.01819318e-02 -1.17585100e-02 3.03332359e-02 2.32851668e-03
      -1.91790052e-03 -1.45414667e-02 -1.12271728e-02 6.12826794e-02
      8.77918899e-02 4.34608646e-02 2.55939234e-02 1.42848529e-02
      4.02497244e-05 -7.98272993e-03 8.29664432e-03 -3.44470935e-03
      2.37156097e-02 8.28078464e-02 5.45031503e-02 -2.00133421e-03
      3.26953754e-02 2.16493867e-02 2.80145984e-02 8.83536320e-03
      -8.62008543e-04 -1.54861622e-02 1.94389746e-02 1.16574736e-02
      -1.40705882e-02 3.95658538e-02 4.22353372e-02 4.11958173e-02
      1.84865333e-02 7.43203890e-03 -2.69332621e-02 1.35028856e-02
      1.15379272e-02 2.85993819e-03 2.02732477e-02 2.78491825e-02
      -5.42546762e-03 1.67183708e-02 -1.44607807e-02 9.25947353e-03
      3.85349318e-02 2.77313162e-02 1.02018099e-03 -1.30580459e-02
      5.30876853e-02 3.77658047e-02 1.53104588e-02 8.55340331e-04
      -2.92971376e-02 3.99222858e-02 3.13128568e-02 -4.15005721e-02
      5.25268689e-02 8.11525714e-03 1.73711386e-02 1.09804617e-02
      1.36875948e-02 -2.67497022e-02 -6.68644905e-03 -3.54307098e-03
      4.22290117e-02 3.53196114e-02 -8.78124963e-03 7.99685810e-03
      1.49000008e-02 2.87713595e-02 -2.53435653e-02 -5.60657308e-03
      -3.46072130e-02 2.32255626e-02 -9.76818334e-03 2.57703494e-02
      1.23529229e-02 1.32641960e-02 -7.77359307e-03 -2.41666455e-02
      -9.74956341e-03 -1.24332225e-02 -3.10824402e-02 -5.51952980e-03
      1.96660273e-02 1.38676660e-02 1.48668382e-02 -1.86737068e-02
      -1.62759777e-02 -9.22541227e-03 -1.13560036e-02 -2.17932388e-02
      4.42748815e-02 3.30156088e-03 -2.03288207e-03 3.84914875e-03
      -9.35041625e-03 -1.82489883e-02 -1.14682447e-02 -3.23986635e-02
      3.33876871e-02 1.95558593e-02 1.04631940e-02 -2.50052923e-04
      -2.25934060e-03 -7.06189126e-03 -2.69888574e-03 -1.66265387e-02
      -1.33785317e-02 1.01837274e-02 -6.22474635e-03 1.19866626e-02
      2.66021993e-02 1.11379866e-02 -2.00142562e-02 3.02241393e-03
      -2.28319559e-02 -4.46706265e-02 -2.74132229e-02 -1.83569305e-02
      5.50972344e-03 -1.61324311e-02 -5.48147876e-03 -3.44631699e-05
      8.51489487e-04 -1.56599861e-02 1.94443006e-03 -1.01005752e-02
      5.51994797e-03 2.01577507e-02 1.19798665e-03 -9.60072316e-03
      -1.83388628e-02 -5.74240275e-03 -9.79534816e-03 6.39995979e-03
      5.69415577e-02 -7.20713846e-03 4.15245071e-02 1.54676950e-02
      -2.28585992e-02 -2.58571412e-02 -2.59220172e-02 -1.76006164e-02
      1.69446021e-02 4.83381189e-02 -2.22986527e-02 -1.48044545e-02
      -1.27361305e-02 -1.71335340e-02 -2.34624255e-03 -2.20608828e-03
      -6.78120879e-03 2.27159541e-02 1.70993097e-02 -1.20395152e-02
      1.30354706e-02 2.20879503e-02 8.80359113e-03 -1.32799777e-03
      -2.17107739e-02 2.13832385e-03 8.19253922e-03 1.65419634e-02
      1.38017526e-02 5.33903483e-03 1.54356603e-02 -4.95551107e-03
      -2.11063325e-02 -1.63952019e-02 -8.12333636e-03 5.35393460e-03
      4.12872508e-02 1.18048033e-02 -1.74819529e-02 -2.40027793e-02
      1.07469140e-02 -9.45091993e-03 -2.71030907e-02 -5.60453488e-03
      2.76970062e-02 3.34649757e-02 9.25389118e-04 6.61382917e-03
      -1.43075245e-03 -1.10247254e-03 4.35454771e-03 -4.50575957e-03
      2.08349363e-03 1.01743909e-02 -1.97317246e-02 2.65282448e-02
      1.85166132e-02 -2.48324890e-02 -5.54086873e-03 1.19379330e-02
      -7.84462597e-03 1.01535302e-02 3.45315263e-02 3.43656121e-03
      6.57098787e-03 -2.96631884e-02 -5.04106795e-03 1.16213784e-02
      -2.23307665e-02 -1.04023255e-02 9.28462949e-03 1.25554837e-02
      3.97962704e-02 2.90715266e-02 -3.35867330e-02 -2.26908084e-03
      1.50686326e-02 -2.58961692e-02 -6.02799328e-03 1.20067205e-02
      -8.19938350e-03 3.12891155e-02 1.44975679e-02 -1.72645617e-02
      -2.52851155e-02 -5.27201639e-03 -2.39933655e-02 -1.50066661e-02
      2.84068435e-02 1.53984139e-02 7.67181674e-03 2.43015736e-02
      1.39199169e-02 1.30155291e-02 2.14059446e-02 -1.78805310e-02
      8.86053126e-03 4.04124102e-03 1.49307530e-02 1.32376114e-02
      1.11964224e-02 -1.22535424e-02 -7.93304108e-03 -9.07921884e-03
      -3.10818180e-02 -1.28043890e-02 1.42604532e-02 -2.90262559e-03
      3.17912623e-02 8.32864456e-03 -9.77578200e-03 3.73415858e-03
      2.27142945e-02 -6.09447854e-03 3.30328417e-04 1.51567562e-02
      -3.16223083e-03 8.40773899e-03 -9.97977797e-03 -3.39927990e-03
      -8.11776053e-03 -6.16595102e-03 1.14366561e-02 -4.42151166e-03
      1.48956047e-03 -1.82463899e-02 1.47687551e-02 -1.18916585e-04
      -7.86815584e-03 -1.24022253e-02 2.58242302e-02 2.43818033e-02
      3.33542041e-02 2.07211562e-02 5.10767708e-03 6.32657856e-03
      -3.71534005e-03 -1.36832306e-02 -1.78034615e-03 3.05190235e-02
      4.74952571e-02 2.06199307e-02 6.35661976e-03 -1.13775777e-02
      -2.27016630e-03 1.18028205e-02 1.11420797e-02 1.91378687e-02
      1.77329518e-02 -5.38816079e-02 5.11355279e-03 1.70276687e-02
      6.82281377e-03 1.48674240e-02 1.30999163e-02 8.33053794e-03
      -2.46792845e-03 6.55987635e-02 2.76898835e-02 -2.29136702e-02
      -1.18085230e-02 -1.99799836e-02 -7.80578423e-03 -1.35790033e-03
      1.63671356e-02 1.76613871e-02 4.06202413e-02 -2.59819329e-02
      -9.57651995e-03 2.19287369e-02 9.17731039e-03 2.74467636e-02
      -3.04285204e-03 -8.83756019e-03 2.23657768e-03 -2.00345907e-02
      -2.65463255e-02 5.90221286e-02 5.79915307e-02 9.72304586e-03
      -9.07817297e-03 1.91511996e-02 -9.96639207e-03 -2.45085601e-02
      -2.38664565e-03 -1.73214730e-02 2.80856676e-02 3.92672382e-02
      2.56333477e-03 1.67848356e-03 2.35544853e-02 -1.34439403e-02
      -6.32991316e-03 2.16315821e-04 -2.23708041e-02 9.50689465e-02
      3.99981290e-02 2.15128306e-02 2.39250679e-02 3.30738239e-02
      -6.15222938e-03 -1.19296461e-02 4.30958755e-02 1.81883182e-02
      5.16002104e-02 2.60635745e-02 5.42286318e-04 1.70424965e-03
      2.11348832e-02 7.01896194e-03 -7.93353934e-03 -9.20898467e-03
      -2.11718623e-02 -3.81907332e-04 3.33701037e-02 3.30416523e-02
      -1.94894290e-03 -1.40054841e-02 4.57125083e-02 5.90781419e-05
      -3.01478487e-02 -8.95113312e-03 -1.06469570e-02 1.76168941e-02
      4.41298485e-02 -2.34016571e-02 3.21640037e-02 1.24402456e-02
      9.72658210e-03 3.16358544e-02 2.68572904e-02 1.86970793e-02
      2.85324808e-02 1.68305822e-02 1.98957026e-02 2.87662558e-02
      2.53518634e-02 -6.74885744e-03 -2.39065867e-02 -2.54133493e-02
      1.89518109e-02 1.22289369e-02 1.34229204e-02 2.23478186e-03
      -4.89264145e-04 3.25442739e-02 2.02358249e-04 5.77156665e-03
      1.25211189e-02 -1.50166452e-02 8.32932163e-03 2.98166275e-02
      -3.77844311e-02 -1.34660862e-02 2.98787523e-02 2.23839767e-02
      1.68180205e-02 -4.84939944e-03 -9.27586015e-03 9.22375638e-03
      4.35729045e-03 -1.73721593e-02 9.84738953e-03 1.70498230e-02
      -1.92477333e-03 -1.06636444e-02 2.72828937e-02 1.23185916e-02
      6.47481671e-03 2.63712108e-02 9.63289384e-03 3.41409221e-02
      -9.49643366e-03 3.12254615e-02 8.36225972e-03 1.60621305e-03
      1.22865895e-04 1.81156525e-03 1.12678520e-02 -4.51247720e-03
      -1.06512783e-02 -4.35757311e-03 1.29553564e-02 9.38420370e-03
      -1.09426258e-02 1.06357522e-02 5.96444355e-04 -1.48560153e-02
      -6.71436824e-03 -1.13236140e-02 1.52218333e-02 1.35451125e-03
      -1.77030975e-03 -1.03957811e-02 1.72093865e-02 1.64380874e-02
      1.54593466e-02 5.67004876e-03 -6.08737720e-03 -1.24503365e-02
      9.91510693e-03 1.97691703e-03 3.21402127e-04 5.42741502e-03
      -2.87121721e-03 -2.59309616e-02 -1.41314110e-02 2.30487008e-02
      2.55358056e-03 -1.23762721e-02 -9.89262573e-03 -1.44846281e-02
      3.17760520e-02 2.56793387e-02 1.49037652e-02 -2.61304211e-02
      -1.82491075e-02 -8.02916661e-03 7.00343307e-03 -8.22276995e-03
      7.74565712e-03 -2.13287515e-03 -1.07614128e-02 1.60749592e-02
      3.88464220e-02 -2.57185325e-02 1.39527665e-02 3.62392291e-02
      2.06402484e-02 1.80566423e-02 -2.55340058e-03 9.69105493e-03
      5.35806688e-03 2.44483985e-02 -4.70959656e-02 -1.37609206e-02
      -2.54748762e-03 4.74843569e-03 7.93554727e-03 7.14867050e-03
      -4.09951434e-04 -3.55565129e-03 -1.78170460e-03 -9.69408918e-03
      -2.73346845e-02 1.48690899e-03 1.56617668e-02 1.29541708e-02
      6.57365052e-03 1.44127151e-02 1.62069332e-02 1.27875879e-02
      -9.45282727e-03 2.23421641e-02 -2.43856455e-03 -4.50295117e-03
      3.80228716e-03 -1.39657187e-03 -1.93161226e-03 -1.12237008e-02
      -4.13733423e-02 9.90451034e-03 3.30710597e-02 -2.55624186e-02
      -6.98420685e-03 7.96708278e-03 8.37482326e-03 -9.75318544e-04
      2.01081969e-02 1.03332829e-02 5.68768010e-02 2.05802824e-02
      -1.50783248e-02 -5.84499491e-03 2.08197301e-03 -1.82905770e-03
      -5.45109250e-03 -1.38900848e-02 -4.84684575e-03 7.03142360e-02
      8.38105381e-03 -3.84565406e-02 -1.28553854e-03 -1.02083748e-02
      -4.55381843e-04 -1.02587752e-02 -1.21921941e-03 1.73539706e-02
      -8.31360929e-03 5.38496161e-03 -2.11407579e-02 -2.28777295e-03
      -1.46272965e-02 4.66017472e-03 1.86312199e-02 2.19241865e-02
      -4.43849666e-03 1.72054786e-02 1.35552231e-03 -1.86687312e-03
      -9.65081807e-03 -3.02626360e-02 2.29886104e-03 1.13525789e-03
      -3.17774666e-03 1.55985849e-02 6.13759905e-02 1.37187559e-02
      -2.44132038e-02 -1.22805210e-02 -1.62660182e-02 -6.84250845e-03
      1.23658869e-02 3.11790984e-02 2.42301878e-02 4.75825556e-02
      4.20529395e-02 1.41619414e-03 -2.60555875e-02 -4.03245017e-02
      -1.11744693e-02 1.65095683e-02 2.05044560e-02 3.84987071e-02
      -4.64581652e-03 -2.50670128e-03 -1.16691424e-03 -3.60534573e-03
      -1.47293881e-02 -8.42463784e-03 2.53539789e-03 -2.16652360e-02
      1.96718201e-02 1.11119319e-02 -1.53067010e-02 -2.38296739e-03
      -2.48083868e-03 -1.13383261e-02 2.71023456e-02 2.76905056e-02
      8.30056518e-03 4.18159515e-02 3.57907079e-02 1.49881840e-02
      2.05144659e-02 -4.37695393e-03 -4.77765650e-02 -1.44043416e-02
      3.74114737e-02 -3.76511295e-03 1.67793892e-02 -2.65782606e-03
      3.50255612e-03 -2.90406775e-03 -2.79429648e-02 -2.19675768e-02
      2.99474392e-02 3.78651246e-02 2.21394864e-03 3.47552374e-02
      1.35259237e-04 1.08375199e-04 -1.08251544e-02 5.39413728e-02
      5.00251986e-02 -5.04776165e-02 -1.74244866e-02 -9.67183523e-03
      -7.63242412e-03 -2.08132318e-04 -1.15212798e-02 5.77979768e-03
      4.71448824e-02 -1.13626663e-02 -2.97954027e-02 -4.82682977e-03
      1.52369007e-03 1.99378282e-02 1.60020161e-02 1.72676742e-02
      -1.83450188e-02 4.67149541e-02 4.51880209e-02 -3.07768472e-02
      -2.99586058e-02 -3.01526533e-03 -2.74250214e-03 1.33493859e-02
      -5.38366009e-03 -1.17156254e-02 3.63059975e-02 5.37161622e-03
      -3.95387448e-02 -1.80380307e-02 2.85206307e-02 2.47824658e-02
      8.67622532e-03 -2.73882393e-02 -3.01462249e-03 1.90047715e-02
      -1.01161962e-02 2.96399705e-02 8.99211224e-03 -3.45768873e-04
      2.88403016e-02 2.48125922e-02 -2.46200152e-02 -2.69509275e-02
      1.64530519e-02 8.99201352e-03 4.32376787e-02 3.43945087e-03
      -1.22983335e-02 9.30999592e-03 3.66254314e-03 -2.88299881e-02
      -2.47926917e-02 3.97319086e-02 -2.03177985e-02 2.06002835e-02
      2.18549464e-02 3.01221125e-02 3.30579057e-02 -5.39602805e-03
      -2.34425031e-02 -1.44461785e-02 3.27912420e-02 3.60660367e-02
      3.77955846e-02 1.77817196e-02 -2.88517633e-03 -3.77328461e-03
      1.38020702e-02 -1.01463832e-02 -1.30132651e-02 2.43640188e-02
      1.61992610e-02 4.53008451e-02 8.03145207e-03 -1.20817646e-02
      1.62514523e-02 1.55944638e-02 -1.22480448e-02 -2.75895391e-02
      -2.89304703e-02 -1.17642218e-02 1.85673535e-02 1.09007331e-02
      -1.70581862e-02 -9.20141523e-04 3.63559928e-03 -7.54043227e-03
      3.26068886e-03 6.63236827e-02 5.29261641e-02 3.24948616e-02
      8.94716883e-04 -1.81670915e-02 1.07358834e-02 1.07791629e-02
      -3.00771836e-02 1.76835489e-02 3.74265946e-02 3.05677298e-02
      1.48075009e-02 -7.21328938e-03 -1.27339773e-02 1.29346428e-02
      1.96301155e-02 7.10973574e-04 -1.81680936e-02 -1.52076585e-02
      8.27525742e-03 2.23224517e-02 -3.09875747e-03 -2.06208741e-03
      -1.34488577e-02 1.23014245e-02 5.12194936e-04 1.59189459e-02
      9.31239221e-03 -5.74095128e-03 -8.95745680e-03 -1.78387966e-02
      -3.51791047e-02 -4.35023941e-02 1.54104084e-02 4.75578345e-02
      3.57540064e-02 3.36627406e-03 3.63761336e-02 -6.96875295e-03
      -1.01372777e-02 7.12267775e-03 -1.66110657e-02 -8.23393557e-03
      4.78551313e-02 1.21184262e-02 1.15787601e-02 1.53795034e-02
      -2.48276182e-02 2.09370144e-02 1.19713452e-02 -1.18437335e-02
      -1.12892280e-03 -5.49852895e-03 -4.94634127e-03 -1.08982692e-03
      -5.45930257e-03 -3.51262488e-03 -1.06242253e-02 -1.35752428e-02
      -7.68848788e-03 -2.11097719e-03 -1.06951231e-02 -3.32371667e-02
      -6.49506925e-03 3.53608723e-03 1.44960182e-02 3.31955566e-03
      1.70430336e-02 3.03513138e-03 1.91110596e-02 2.84730140e-02
      -5.76011464e-03 -4.95783472e-03 7.56234303e-03 9.90622118e-03
      6.29791990e-03 9.67709348e-03 -2.77694631e-02 5.11925258e-02
      3.45804542e-02 9.74069536e-03 -2.76630148e-02 1.88462660e-02
      -2.11099293e-02 -8.42696335e-03 1.92285795e-02 -1.09022176e-02
      -3.75876315e-02 -3.17855328e-02 -1.89886224e-02 -3.78733198e-03
      3.22280894e-03 3.61482147e-03 1.94842039e-04 1.94415962e-03
      -7.08399387e-03 1.43548269e-02 -2.33683493e-02 -1.63415577e-02
      -7.10591394e-03 -5.99056296e-03 5.43141097e-04 3.88570625e-04
      1.30784335e-02 1.88503489e-02 4.37631868e-02 1.55853089e-02
      7.37076218e-04 -1.54203987e-02 -6.19456032e-03 -2.26567332e-02
      -6.69268018e-04 8.07414530e-04 -2.47794134e-03 1.85648650e-02
      4.68143784e-02 -7.43879820e-04 -1.46288043e-02 -1.24136312e-02
      -2.21023206e-02 -1.57659315e-02 -1.70136429e-02 -3.16790305e-03
      2.74129305e-02 5.46786422e-03 -2.01761369e-02 -3.50219500e-03
      -3.10054515e-03 -7.61564495e-03 -1.53645128e-02 -2.59858239e-02
      -1.05524426e-02 8.40020999e-02 3.23247015e-02 -6.47122264e-02
      -1.55646782e-02 -1.17849903e-02 -2.29146029e-03 -1.41781615e-02
      -6.66135177e-03 1.94282662e-02 1.48305753e-02 2.99018100e-02
      -1.37815233e-02 -1.65295647e-03 -8.14236887e-03 -1.48143340e-02
      -3.12280953e-02 -2.31345836e-02 -2.41066404e-02 2.96393149e-02
      4.01374474e-02 -1.96490716e-02 -3.30339139e-03 -8.25764891e-03
      -7.23058498e-03 -1.72984749e-02 1.18027395e-03 -2.68092789e-02
      5.51885851e-02 1.65436268e-02 -3.91454734e-02 -2.93677878e-02
      -4.03291639e-03 -1.61288062e-03 5.80383372e-03 2.71300711e-02
      3.16581838e-02 6.19093776e-02 4.54319175e-03 -2.72188541e-02
      -5.29098660e-02 -3.32791582e-02 3.71964555e-03 1.22070862e-02
      4.81464565e-02 2.69949473e-02 3.37629467e-02 2.39032172e-02
      -2.76599936e-02 -5.15748281e-03 2.93771513e-02 7.98037369e-03
      -1.87682062e-02 1.80809144e-02 -5.15041919e-03 1.32609159e-02
      -1.29834320e-02 -3.50639522e-02 -1.97881795e-02 1.01605291e-02
      2.58270260e-02 2.86748521e-02 4.07983139e-02 5.03409430e-02
      2.06243992e-02 -8.11903551e-03 5.10995742e-03 -2.50657350e-02
      -3.64762731e-02 2.84743169e-03 4.77788560e-02 1.69232376e-02
      1.87142082e-02 8.19429010e-03 1.46087946e-03 7.32609862e-03
      -5.03652124e-03 1.41709568e-02 2.84927245e-02 4.21671867e-02
      -8.57628975e-03 7.52125587e-03 -2.73533594e-02 -3.44940908e-02
      -1.02209458e-02 1.20421631e-04 1.70639027e-02 3.04992776e-02
      4.13771309e-02 4.00985964e-02 3.03625669e-02 -8.48286599e-03
      -2.31693499e-02 1.22379456e-02 4.80601341e-02 2.73221433e-02
      -2.89679482e-03 1.81511808e-02 -7.38783088e-03 1.01792542e-02
      3.86820035e-03 9.97156650e-03 -6.30341354e-04 2.29473952e-02
      5.41620441e-02 -2.35551819e-02 -2.54956894e-02 -3.71544785e-03
      -2.05192761e-03 -1.02049240e-03 1.84377667e-03 -2.12095883e-02
      4.14158143e-02 2.09573098e-02 -4.19159792e-02 -1.89398397e-02
      1.34581868e-02 2.40296107e-02 -5.98609913e-03 5.06530004e-03
      4.60064010e-04 2.59496067e-02 5.39834574e-02 1.04640638e-02
      -3.09430808e-02 8.17079330e-04 6.43547683e-04 -7.17875082e-03
      -1.39392456e-02 -3.08048204e-02 5.38559593e-02 2.24255887e-03
      -1.41196344e-02 -1.80445407e-02 1.74194686e-02 1.96105819e-02
      -6.83175167e-03 -2.62181349e-02 -2.62324996e-02 3.73944603e-02
      5.45319449e-03 -4.70776530e-03 9.83117241e-03 1.94948427e-02
      1.34071214e-02 -2.63990425e-02 -2.48538535e-02 -1.49103133e-02
      2.84735635e-02 5.68767563e-02 3.95088308e-02 -2.58593122e-03
      -2.42703389e-02 -2.87562590e-02 -3.07713691e-02 -4.48608510e-02
      -3.12030390e-02 6.19252063e-02 3.88361812e-02 1.48114376e-02
      7.33606983e-03 1.16207143e-02 5.63294766e-03 -4.66114767e-02
      -3.85268778e-02 -1.46810142e-02 6.69779629e-02 4.73008789e-02
      5.96213080e-02 1.14463009e-02 -3.70991491e-02 -4.97411825e-02
      -2.21894775e-02 -7.87987467e-03 -2.79866648e-03 3.92006636e-02
      5.12087122e-02 2.17663795e-02 1.57383140e-02 -1.60598233e-02
      -1.80323441e-02 -1.34681845e-02 -1.50734372e-02 8.38751346e-03
      3.26979347e-02 2.72442829e-02 -1.19043067e-02 1.57998432e-03
      1.41861232e-03 -1.97341796e-02 -1.07065905e-02 1.20875090e-02
      5.54834818e-03 2.61291452e-02 6.54122382e-02 5.96866757e-02
      5.65611944e-02 1.67645211e-03 -3.03093772e-02 -7.82594271e-03
      1.21968323e-02 -5.57208899e-03 7.56675191e-03 2.56096963e-02
      1.21765314e-02 4.23329324e-02 5.87855838e-03 -1.43069727e-02
      -9.27306898e-03 3.56110223e-02 1.08091813e-02 2.19522957e-02
      2.78689209e-02 -1.64390635e-02 -8.85208044e-03 -8.82163737e-03
      -2.80391704e-02 9.69877746e-03 3.66856046e-02 -2.24657543e-02
      1.99610647e-03 -2.25012307e-03 -1.98893491e-02 1.41870361e-02
      1.47744464e-02 -2.08442900e-02 -3.43465135e-02 2.54025515e-02
      -5.13806613e-03 3.32527906e-02 6.12771548e-02 2.81402227e-02
      1.36033515e-03 -3.09832208e-02 -4.01304401e-02 7.86814094e-03
      4.39828895e-02 -1.28809372e-02 1.38134258e-02 1.37398206e-02
      -6.03976799e-03 1.52968932e-02 -7.43032852e-03 -3.25800665e-02
      -1.38980458e-02 1.30951194e-05 -2.39536026e-03 -1.60849746e-02
      -1.40846241e-02 -7.12806871e-03 -7.71193020e-03 1.28730498e-02
      -1.39879165e-02 3.38730477e-02 3.83851379e-02 -3.13942018e-03
      -2.99774092e-02 -1.88945532e-02 -2.46758815e-02 -1.98432300e-02
      -1.10992678e-02 -1.89924296e-02 2.68942807e-02 6.60746470e-02
      1.93718132e-02 -4.49448032e-03 -3.33397351e-02 -2.89712735e-02
      -1.55199952e-02 -6.13811286e-03 -3.38867158e-02 3.81820612e-02
      7.75086433e-02 -1.46392295e-02 -9.85145010e-03 -2.03739293e-02
      -3.31791230e-02 -3.51112075e-02 -3.92863005e-02 -5.51050231e-02
      4.41015512e-02 5.04561700e-02 -8.39193724e-03 -1.22616962e-02
      -5.82213840e-03 -1.86567567e-02 -1.32741854e-02 -1.03048971e-02
      -3.40577438e-02 3.28895859e-02 4.03048769e-02 -2.83931904e-02
      -1.08401617e-02 -8.12021364e-03 -1.92932468e-02 -1.96618494e-02
      -1.47048468e-02 -4.66920175e-02 5.76744601e-02 6.27358854e-02
      -2.49160137e-02 -6.31630933e-03 -5.92424395e-03 -1.92047209e-02
      -2.02786904e-02 -6.90484373e-03 -2.79383454e-02 4.16992567e-02
      4.32438515e-02 -3.06691211e-02 -9.51203890e-03 -1.83915962e-02
      -2.32561994e-02 -1.83063149e-02 4.30765282e-03 -2.28191242e-02
      7.33520044e-03 4.28457931e-02 2.66702054e-03 -7.61936011e-04
      -6.12529693e-03 -7.56597007e-03 -1.42646423e-02 -1.01285651e-02
      -2.49695182e-02 2.56952196e-02 3.79537195e-02 2.37581227e-02
      1.09501025e-02 2.69519864e-03 -8.91148392e-03 -1.19389491e-02
      -8.88206158e-03 -3.40859741e-02 2.16054660e-03 3.19848470e-02
      1.85246430e-02 -7.58071197e-04 -7.19764736e-03 -2.14428399e-02
      -1.44367767e-02 4.86742443e-04 -1.04118139e-02 1.38747878e-02
      5.00603989e-02 4.49529365e-02 1.39733683e-02 2.07535384e-04
      -2.67036706e-02 -1.87154878e-02 -1.62594076e-02 -2.44290289e-02
      3.53709944e-02 4.80385982e-02 -9.53741185e-03 2.15647742e-02
      2.57620849e-02 -7.28006195e-03 -1.91378836e-02 -5.08542359e-03
      -2.35591456e-02 1.54124722e-02 -1.22396927e-02 8.35813640e-04
      1.70213468e-02 1.52178025e-02 2.25168988e-02 4.63696569e-03
      2.69321017e-02 5.21253189e-03 3.90070938e-02 5.01893088e-02
      2.33784523e-02 2.81490944e-02 -3.68771213e-03 -3.50719243e-02
      -3.16906981e-02 -1.54729458e-02 -8.47970601e-04 2.80841663e-02
      1.17344987e-02 2.21501905e-02 3.18650976e-02 -8.12879007e-04
      -6.39049290e-03 -2.87647592e-03 1.49069680e-02 1.57163404e-02
      -2.12808773e-02 -1.71109904e-02 -1.00640375e-02 2.59571779e-03
      9.05357767e-03 1.68634094e-02 1.77730676e-02 2.00365782e-02
      6.58933353e-03 -3.11310776e-03 -1.27971889e-02 1.03252409e-02
      3.35632935e-02 -9.61086340e-03 -1.33387186e-02 1.35885021e-02
      1.18149063e-02 1.41578661e-02 -3.24047022e-02 -1.73369925e-02
      2.01113261e-02 1.15887728e-02 3.00521404e-02 3.52787711e-02
      1.56926494e-02 9.09856334e-03 -1.79581232e-02 -1.00589087e-02
      7.86481053e-03 3.71599942e-02 2.15488635e-02 9.64535866e-03
      2.75413264e-02 2.02921089e-02 1.97137687e-02 8.72706156e-03
      -1.15958822e-03 -5.77780697e-03 -1.29765105e-02 6.08006353e-03
      7.40536898e-02 -7.03769270e-04 -1.52223771e-02 -1.99034912e-04
      9.36016499e-04 -1.10802725e-02 -2.23090351e-02 -3.88664566e-02
      7.94307888e-03 4.66619246e-02 -1.14737740e-02 -1.43748699e-02
      4.40022862e-03 1.52251599e-02 -4.59089456e-03 -1.67048275e-02
      -3.75353210e-02 -3.39674484e-03 8.09015408e-02 2.01738440e-02
      -2.61824597e-02 -6.64087851e-03 -7.04033242e-04 -1.96473431e-02
      -3.24059799e-02 -4.77962233e-02 -1.23156514e-02 5.70470840e-02
      2.65355110e-02 -7.66214728e-03 -3.12119676e-03 -5.33883600e-03
      -2.55096424e-02 -3.99870463e-02 -3.54646929e-02 2.94829626e-02
      5.66535853e-02 2.37429515e-02 2.85084359e-03 1.69382698e-03
      -2.88406317e-03 -4.64961790e-02 -3.76485176e-02 -2.98902392e-02
      5.95147014e-02 6.27313778e-02 4.96328659e-02 1.32175786e-02
      -1.10245682e-02 -3.58832031e-02 -3.40497606e-02 -4.04390655e-02
      -6.85021132e-02 6.50147535e-03 4.62770835e-02 5.03941551e-02
      3.12095229e-02 -6.80365926e-03 -2.09247544e-02 -6.25178739e-02
      -4.48314287e-02 -7.42691234e-02 3.72020225e-03 1.34985857e-02
      5.66333681e-02 2.98981890e-02 1.78058334e-02 -2.01618969e-02
      -1.98933501e-02 -5.58064785e-03 1.06196583e-03 1.68453846e-02
      1.83460675e-02 3.49902809e-02 2.17177626e-02 2.53857719e-03
      -2.21088324e-02 -1.03534656e-02 -1.92655332e-03 -2.04595849e-02
      -2.21586600e-02 9.60112084e-03 1.76063664e-02 2.15177145e-02
      2.63200793e-03 -3.96246500e-02 -2.90049892e-02 1.18325241e-02
      3.23506333e-02 2.23962963e-02 7.73528637e-03 9.56887659e-03
      3.64438519e-02 1.67578980e-02 6.10821648e-03 3.84371877e-02
      -1.67698991e-02 3.38702388e-02 -1.34387529e-02 -3.45062092e-02
      1.54967257e-03 1.55146746e-02 3.00190412e-02 -3.63581851e-02
      -2.55047716e-02 3.04101184e-02 -1.24843717e-02 -1.58915631e-02
      -1.43736775e-03 -1.64831537e-04 9.46708315e-04 -3.79489409e-03
      -2.73811668e-02 1.54611301e-02 6.16723821e-02 2.50282809e-02
      -2.32890807e-02 -2.00046189e-02 -2.16473248e-02 -1.24761201e-02
      -1.35873072e-02 -4.90570255e-02 3.90496515e-02 1.30355405e-02
      -6.46165805e-04 -2.48087235e-02 -3.24704312e-02 -1.28878104e-02
      1.00814253e-02 3.82669829e-02 4.65025334e-03 4.08700183e-02
      8.23723376e-02 -4.37791180e-03 -1.66258067e-02 -1.53476512e-02
      -1.51023390e-02 -1.48782553e-02 -4.83197439e-03 -1.45597020e-02
      3.09412237e-02 6.94081113e-02 2.48433333e-02 -2.95285578e-03
      -1.67083666e-02 -2.08469946e-02 -1.38172600e-02 -1.71756968e-02
      -4.22379486e-02 3.60865444e-02 2.92035211e-02 1.12213558e-02
      2.15620268e-03 -6.90566376e-03 -2.23271362e-02 -3.17201242e-02
      -2.45575923e-02 -5.25334775e-02 5.36485277e-02 5.21107465e-02
      2.52740532e-02 -3.55241890e-03 -5.62977220e-04 -1.20257791e-02
      -1.23469885e-02 -2.34258343e-02 -4.97487150e-02 4.03767563e-02
      2.08768137e-02 -8.52463581e-03 5.52269816e-03 5.09976409e-03
      -1.35023696e-02 -1.92987788e-02 -2.37404462e-02 -4.17465530e-02
      6.40706792e-02 3.55231166e-02 -1.28143625e-02 1.58707192e-03
      -1.14975008e-03 -1.47309909e-02 -1.44187948e-02 4.74423496e-03
      -2.09666863e-02 4.02046032e-02 1.77813452e-02 -9.46796685e-03
      -2.74104485e-03 -1.67676061e-02 -1.66416634e-02 -1.28438696e-02
      2.76238634e-03 -2.89786793e-02 8.48172046e-03 5.59508651e-02
      1.88777242e-02 -3.57247610e-03 -2.96959362e-04 -1.30461948e-02
      -1.60117187e-02 -1.21276639e-02 -5.58668151e-02 2.00972799e-02
      6.40064031e-02 4.92973179e-02 -9.90765076e-03 -1.12602608e-02
      -1.51681406e-02 -2.29969677e-02 -2.35446114e-02 -5.49093783e-02
      2.17873473e-02 3.04645784e-02 1.67617444e-02 6.54470525e-04
      -1.45910122e-02 -2.11729091e-02 -1.17096752e-02 8.50140874e-04
      -1.67059172e-02 1.68263670e-02 7.13337511e-02 4.28836979e-02
      2.80922279e-03 -1.76017880e-02 -3.66689079e-02 -2.36389134e-02
      -2.06692168e-03 -6.13057148e-03 3.25713716e-02 4.54219356e-02
      2.51443405e-02 -5.56725124e-03 -8.07775464e-03 -1.57927815e-02
      -1.72450189e-02 -1.78488828e-02 -7.47534726e-03 3.07894237e-02
      5.05213998e-02 3.90640683e-02 6.71425322e-03 -7.63012981e-03
      -2.17123013e-02 -2.31197681e-02 -7.24921189e-03 -3.42440903e-02
      1.17354747e-02 5.08298427e-02 2.28357166e-02 7.85416458e-03
      -1.75397433e-02 -4.36846912e-02 -1.14385998e-02 6.06859382e-03
      9.17891599e-03 2.07090601e-02 9.20987315e-03 1.78239178e-02
      7.14245671e-03 -2.61441972e-02 -1.79582555e-02 -2.33558170e-03
      2.07859538e-02 3.30322422e-02 2.08646655e-02 4.93781790e-02
      1.07297143e-02 7.59691978e-03 2.72846883e-05 -1.57200545e-02
      -3.60924494e-03 -3.69084696e-03 -1.92664750e-02 9.20707546e-03
      3.84923927e-02 1.69124790e-02 8.41509318e-04 5.90179954e-03
      -2.14601718e-02 -3.22750071e-03 6.76804688e-03 3.10039874e-02
      -3.26301083e-02 -5.22797368e-03 4.13417816e-03 8.46331567e-03
      1.21065807e-02 9.96645726e-03 -1.19122183e-02 -9.95199569e-03
      -6.03803433e-03 4.08004364e-03 2.13541240e-02 2.44930200e-02
      4.78692679e-03 -7.14575825e-03 2.77983285e-02 -8.85943137e-03
      -7.28543336e-03 3.43310507e-03 1.57176238e-02 2.81538703e-02
      1.47414319e-02 1.29301660e-02 5.65925194e-03 -2.36510877e-02
      -1.36737423e-02 -1.34518025e-02 3.68337035e-02 3.93741019e-02
      2.94140466e-02 6.93859439e-03 -1.26737189e-02 1.80118121e-02
      1.47104068e-02 -3.69199691e-03 -1.95095614e-02 2.39180308e-02
      -3.23028606e-03 -1.23581085e-02 -2.57912539e-02 -1.93782512e-03
      8.47881734e-02 4.50055208e-03 -1.84403136e-02 -6.13226788e-03
      -2.24252115e-03 -1.66367050e-02 -2.33146660e-02 -4.80413996e-02
      -2.61105634e-02 5.58163263e-02 2.74426956e-02 -1.16750356e-02
      -9.28367116e-03 -6.49852725e-03 -3.03590973e-03 -1.03126084e-02
      -2.39791945e-02 1.52932052e-02 6.86454326e-02 1.22119803e-02
      -3.09441388e-02 -1.80147048e-02 -6.69071823e-03 -1.51732368e-02
      -3.05391811e-02 -5.89659065e-02 -7.02580262e-04 5.03918678e-02
      4.72585745e-02 -1.53777488e-02 -2.12951489e-02 -1.32217426e-02
      -2.82930993e-02 -2.78098453e-02 -4.78422642e-02 -1.98458992e-02
      3.38164382e-02 6.98497817e-02 4.04190905e-02 -8.41252971e-03
      -1.26097854e-02 -3.18914354e-02 -3.21653560e-02 -6.34119138e-02
      -1.24312649e-02 2.82677487e-02 7.68261105e-02 5.00582382e-02
      2.98971068e-02 5.45460125e-03 -2.76472196e-02 -2.94078365e-02
      -4.77531999e-02 -4.40352298e-02 2.70856619e-02 6.66166022e-02
      6.74473569e-02 -5.88955823e-03 -2.36507114e-02 -7.71273859e-03
      -2.02744510e-02 -5.22329174e-02 -5.93786361e-03 2.26268917e-02
      8.30230936e-02 9.85056907e-02 4.80031371e-02 3.25297192e-02
      1.87043671e-03 1.12781469e-02 1.75421424e-02 -1.23823974e-02
      -2.61913203e-02 1.69995315e-02 4.63823527e-02 2.46528108e-02
      3.03741731e-02 3.96822095e-02 1.11943968e-02 4.06089723e-02
      -1.37730222e-02 -4.01916020e-02 -3.84578295e-03 2.23245583e-02
      2.45217513e-02 -1.81625672e-02 -5.90320583e-03 -4.60840529e-03
      1.29531126e-03 -9.94201377e-03 -1.53686786e-02 2.56034527e-02
      5.25852926e-02 1.80692244e-02 3.55541557e-02 -2.93224342e-02
      -7.74586620e-03 3.14040333e-02 1.08796274e-02 -1.17556145e-02
      -1.07446266e-02 2.99949721e-02 -1.66208725e-02 -2.30881944e-02
      5.17375171e-02 1.87122058e-02 2.16037314e-03 -3.05540254e-03
      -1.24784522e-02 -8.05792585e-03 9.33859590e-03 3.01762018e-02
      2.90097320e-03 2.65917536e-02 2.78355051e-02 -5.29905269e-03
      1.13270548e-03 7.63674872e-03 6.10677467e-04 2.24727090e-03
      1.28354440e-02 -8.17265175e-03 -3.05960961e-02 -1.40955867e-02
      2.49350667e-02 1.92822460e-02 1.15028480e-02 -4.72434564e-03
      1.98731143e-02 2.54493840e-02 -1.71714947e-02 -1.80365692e-03
      -5.81058161e-03 2.12861784e-02 1.96245611e-02 2.00655647e-02
      2.31832685e-03 1.30559616e-02 1.66634414e-02 9.67795961e-04
      3.57601568e-02 2.24484354e-02 1.93197187e-03 -7.57376663e-03
      6.09099353e-03 -9.03575914e-04 -4.78064030e-05 2.01939209e-03
      -1.87665094e-02 4.69891578e-02 3.49308513e-02 4.82263044e-03
      2.76340288e-03 9.58373491e-03 -1.03239436e-02 -7.41034374e-03
      -7.84630049e-03 -1.35106724e-02 2.91893501e-02 2.55867317e-02
      -2.19188910e-03 -1.41648820e-03 4.06090403e-03 1.18607958e-03
      -1.19980995e-03 7.20783323e-03 -2.28565317e-04 4.55586314e-02
      2.76720133e-02 -5.68384025e-03 -3.42241663e-04 3.72366456e-04
      -4.43513179e-03 -3.10621806e-03 -1.21545820e-02 6.86393760e-05
      1.30081922e-02 3.57599407e-02 1.67385116e-02 -9.89045249e-04
      -2.85199931e-04 -9.89851449e-03 -8.80716182e-03 -8.70320667e-03
      -3.50635201e-02 2.11370271e-02 5.67827076e-02 3.07148267e-02
      -1.08773680e-02 -8.88180919e-04 -8.82698782e-03 -1.40194297e-02
      -1.63782574e-02 -3.66359502e-02 3.88929583e-02 6.42594993e-02
      2.44260486e-02 -2.59616179e-03 -1.12653896e-03 -5.11989882e-03
      -8.33175052e-03 -2.46445369e-02 -2.49856003e-02 3.80146094e-02
      5.15676774e-02 3.39448340e-02 -1.16415126e-02 4.30662744e-03
      -2.58282921e-03 -1.97679549e-02 -1.48913767e-02 -3.08382735e-02
      1.69989206e-02 1.55285057e-02 1.00261578e-02 -3.93895153e-03
      -2.62825959e-03 -6.91987108e-03 -7.33676832e-03 -4.98019671e-03
      3.87678645e-03 3.74468341e-02 4.96922396e-02 1.89561322e-02
      8.91738292e-03 9.11629852e-03 -1.44648692e-02 -1.71783064e-02
      -2.58461572e-02 -2.95857750e-02 4.16968130e-02 2.33689249e-02
      -1.13529284e-02 -9.52737965e-03 -5.82763096e-05 8.35661218e-03
      -3.83445341e-03 -5.03413103e-05 5.87767735e-03 4.36060689e-02
      3.16581316e-02 -1.49350055e-02 7.63109094e-03 5.76622132e-03
      -1.11532658e-02 -1.31428549e-02 -2.19562985e-02 -2.14394350e-02
      4.04703468e-02 5.33540361e-02 7.48589821e-03 1.14146871e-02
      2.23865043e-02 -6.64046500e-04 -2.47826222e-02 -2.51900144e-02
      -3.92369851e-02 1.56493261e-02 2.93216910e-02 1.19814109e-02
      1.39096612e-02 4.69173491e-03 -5.03627770e-03 -1.19853858e-02
      -2.77964841e-03 1.87736731e-02 5.02129085e-02 5.02835773e-02
      -4.07033600e-03 1.38910096e-02 9.88510903e-03 -1.04167312e-03
      -4.60412502e-02 -2.79312637e-02 -3.19064818e-02 2.25663539e-02
      2.69132797e-02 -7.95180723e-03 1.61152314e-02 5.75974677e-03
      5.76084992e-03 -1.03103528e-02 5.19447355e-03 4.31802403e-03
      6.15772372e-03 2.54265536e-02 2.61970311e-02 9.65501554e-03
      3.43842694e-04 -2.15686783e-02 -1.93957742e-02 -1.39877470e-02
      3.18908468e-02 2.87619382e-02 1.97721440e-02 3.18124406e-02
      -2.37831427e-03 1.77038144e-02 2.17310768e-02 8.96559283e-03
      -1.08953649e-02 1.48923658e-02 2.06837114e-02 2.25719102e-02
      3.99448797e-02 4.12445003e-03 -3.08211781e-02 -2.89063174e-02
      -1.70099922e-02 -1.16811385e-02 6.44859904e-03 2.51862332e-02
      4.95117977e-02 4.75733094e-02 -1.07178660e-02 1.84697332e-04
      -6.71277661e-03 -1.06607401e-03 -1.12055494e-02 2.24142219e-03
      -2.06998293e-03 -6.35392126e-03 -9.02073923e-03 2.07712222e-02
      6.82559460e-02 8.50727595e-03 -3.20389196e-02 -1.27514154e-02
      -5.29584382e-03 -1.51486527e-02 -1.61823258e-02 -3.49654518e-02
      -1.56808756e-02 4.65679057e-02 2.12983489e-02 -7.82613817e-04
      -1.54381692e-02 -1.39874816e-02 -8.52382090e-03 -3.90206813e-03
      -1.19641367e-02 1.45749878e-02 4.76599075e-02 3.38505767e-02
      -2.88410136e-03 -1.79794729e-02 -5.04157227e-03 -2.81964894e-02
      -5.90664614e-03 -1.91739555e-02 -2.69274171e-02 2.13261452e-02
      5.70116602e-02 7.60293985e-03 2.24417858e-02 1.28017855e-03
      -1.34586431e-02 -1.30807022e-02 -1.78426038e-02 -3.83417271e-02
      -7.70326704e-03 5.78680262e-02 7.51187354e-02 1.12040713e-02
      -6.42009499e-03 1.30373770e-02 4.80661774e-03 -1.47091551e-02
      -6.76920346e-04 1.14025613e-02 6.43727034e-02 6.22127317e-02
      4.97670025e-02 4.09563705e-02 1.72339249e-02 2.71712197e-04
      3.85921891e-03 -3.13516222e-02 -1.62218548e-02 1.39018632e-02
      2.49322392e-02 3.15296873e-02 2.07566097e-03 1.16546499e-02
      3.19120549e-02 1.44524034e-02 -1.67589088e-03 6.15674583e-03
      -1.61558110e-05 6.74379012e-03 2.47301366e-02 1.74771640e-02
      1.64091140e-02 3.35887782e-02 1.28387539e-02 5.63207502e-03
      7.44268764e-03 1.01894587e-02 1.69158857e-02 -4.65057138e-03
      2.46027503e-02 -6.34931354e-03 4.76960093e-03 4.76888791e-02
      1.51116420e-02 1.54978530e-02 -4.25135670e-03 8.81242659e-03
      -2.15335786e-02 -3.22186649e-02 5.25887348e-02 6.19506612e-02
      1.53168673e-02 3.06098629e-03 1.01232929e-02 -1.58025082e-02
      -1.72460750e-02 -3.43761477e-03 2.67061181e-02 4.06999327e-02
      5.39461412e-02 1.98109783e-02 4.70325234e-04 1.43439798e-02
      -4.85143345e-03 -1.36387469e-02 -4.00747135e-02 5.32226288e-04
      4.90628462e-03 -1.08976867e-02 1.82784256e-02 8.97541363e-03
      7.96317402e-03 -3.40099842e-03 7.34074134e-03 8.83679464e-03
      -2.01270767e-02 2.62059532e-02 1.33926393e-02 1.24949869e-02
      8.24615639e-03 1.96645968e-03 -4.04549856e-03 -6.86471304e-03
      -5.02818357e-03 -1.18257180e-02 6.40292540e-02 3.13454792e-02
      5.79212978e-03 1.69590418e-03 -3.60181136e-03 -9.11463751e-04
      -7.54773617e-04 -1.30176628e-02 -1.23484153e-02 2.40341518e-02
      2.38565877e-02 -7.03557860e-04 7.90262595e-03 -1.32776909e-02
      -1.16515737e-02 -8.44206661e-03 -1.91090070e-02 -7.12911598e-03
      6.31158333e-03 -1.44202746e-02 -5.85576613e-03 5.37117291e-03
      -2.70055054e-04 -1.61419611e-03 -7.59721966e-03 -8.28272663e-03
      -8.24884418e-03 5.92113212e-02 -7.96797592e-03 -1.88568980e-02
      -5.66076208e-03 -7.16084382e-03 -4.85229492e-03 -2.52436777e-03
      -4.87409206e-03 7.92954490e-03 5.21380194e-02 1.34766940e-02
      -2.52120029e-02 4.24802350e-03 -1.02360453e-02 -7.74674257e-03
      -1.14398170e-02 -1.57076549e-02 -7.13646738e-03 4.84105907e-02
      1.90529805e-02 -4.23708521e-02 4.44193278e-03 -7.07118399e-03
      -1.38230976e-02 -3.16483621e-03 1.06283491e-02 6.59829518e-03
      3.48585248e-02 3.69242243e-02 1.94485355e-02 4.85388143e-03
      -3.38411937e-03 -4.05270839e-03 -1.35605438e-02 -1.75259616e-02
      -8.20399169e-03 7.82270171e-03 6.24739118e-02 2.12055519e-02
      6.18816493e-03 1.54491118e-03 7.31534511e-03 -3.00332699e-02
      -3.57168727e-02 -3.48933041e-02 4.28648144e-02 3.68078724e-02
      -9.59900301e-03 1.81418210e-02 3.50132794e-03 1.68601458e-03
      -7.38331350e-03 4.03830409e-03 1.18995635e-02 5.41325193e-03
      4.64744158e-02 -2.20443662e-02 1.55390170e-03 1.19165040e-03
      1.40885245e-02 -9.93386470e-03 -2.85539124e-02 -2.28367150e-02
      2.41561495e-02 1.96110811e-02 -6.27775630e-03 -2.20534531e-03
      8.41555372e-03 2.96387002e-02 3.62030417e-03 1.09614928e-04
      -2.71061971e-03 3.94185036e-02 9.56992619e-03 -3.67259718e-02
      -1.83350488e-03 1.13111259e-02 1.87800433e-02 -4.23146179e-03
      -5.32932347e-03 -8.79073702e-03 2.37015579e-02 1.76910106e-02
      -3.57727185e-02 -6.80096401e-03 2.09411141e-02 3.39050107e-02
      8.58741347e-04 -3.07708234e-02 -1.14123188e-02 3.75180468e-02
      -2.20320071e-03 -4.28495370e-02 -1.20290490e-02 3.68737876e-02
      3.54682021e-02 -1.10305368e-03 -3.28410621e-04 -2.14490537e-02
      4.69663516e-02 1.77155957e-02 -1.53455194e-02 -4.41358378e-03
      5.42504108e-03 1.87823996e-02 -1.94735620e-02 -2.53997259e-02
      -4.12531756e-03 2.22999174e-02 6.05520280e-03 -1.48909651e-02
      3.09150410e-03 1.24733010e-02 2.76605748e-02 -1.00584906e-02
      -3.61510925e-03 1.52649451e-02 4.32067290e-02 7.06838584e-03
      -3.03515140e-02 -9.77990218e-03 8.72669183e-03 2.34344862e-02
      7.17568304e-03 -2.10154261e-02 -9.64230672e-03 4.09307815e-02
      1.29276998e-02 -4.60597873e-02 -1.17758391e-02 1.90935470e-02
      3.84840742e-02 -1.78279751e-03 4.65628412e-03 2.93685496e-02
      2.98410859e-02 1.67870857e-02 9.46209487e-03 -2.55080722e-02
      -1.71662439e-02 -8.84395931e-03 -2.37476081e-02 -2.54673860e-03
      6.11854997e-03 2.33487561e-02 3.09196413e-02 3.30999345e-02
      -1.54761765e-02 9.45753232e-03 4.50010225e-03 -4.04584775e-04
      -4.28023341e-04 -9.71313845e-03 2.93472987e-02 7.47835543e-03
      -2.07175035e-02 -2.65617613e-02 -9.16722976e-03 2.75678616e-02
      -5.08882586e-05 -9.89934150e-03 -2.20334114e-04 9.68915503e-03
      -1.60869546e-02 1.14313746e-02 2.66777668e-02 1.73571911e-02
      4.76762690e-02 -1.62302684e-02 -8.79456848e-03 -1.91095974e-02
      -6.74009928e-03 -4.64885589e-03 -1.08074453e-02 2.35185749e-03
      7.79560581e-03 3.22615281e-02 2.92044692e-02 -8.67455080e-03
      -5.55633148e-03 -5.02326479e-03 1.91916805e-03 -1.48606859e-02
      -2.98708156e-02 -1.83945510e-03 4.01115865e-02 2.49911193e-02
      2.75639482e-02 1.06876707e-02 -6.92285597e-03 -1.01285866e-02
      -1.12380087e-02 5.82907209e-03 1.26706408e-02 1.37956338e-02
      5.62320687e-02 4.16388921e-02 -2.72997562e-03 2.04122402e-02
      3.84396903e-04 -1.89702939e-02 -2.46213488e-02 -2.43532993e-02
      -1.50936302e-02 3.24321836e-02 4.46662717e-02 2.95847207e-02
      2.30244137e-02 3.66505124e-02 1.83892734e-02 -5.19414060e-03
      -1.19641460e-02 -1.05792163e-02 -6.48315018e-03 6.18889788e-03
      4.50280914e-03 2.24103015e-02 5.71183152e-02 2.36486979e-02
      -1.01561658e-02 -8.48392304e-03 -1.45083144e-02 -1.46909552e-02
      -3.46186594e-03 -7.51328655e-03 6.42054901e-02 7.59230778e-02
      2.71796510e-02 8.20642617e-03 -2.64749192e-02 -2.74829157e-02
      -1.80602036e-02 -2.31194198e-02 2.73453612e-02 5.34006059e-02
      7.47931004e-02 2.48799473e-02 -6.83852797e-03 -1.89864859e-02
      -2.49692500e-02 -3.06860935e-02 -3.98932956e-02 -2.77267769e-02
      5.21558784e-02 3.45604829e-02 3.85015330e-04 -1.65362637e-02
      -1.69806927e-02 -2.08840631e-02 -2.29409058e-02 -2.06402019e-02
      1.37095188e-03 8.68889540e-02 4.80168052e-02 -1.16946793e-03
      -1.77100375e-02 -1.58941634e-02 -1.95608586e-02 -1.74141284e-02
      -2.98509989e-02 -4.81409999e-03 6.70997128e-02 2.98519302e-02
      -1.12204906e-02 -1.84920877e-02 -2.12750323e-02 -1.66124124e-02
      -1.35522028e-02 -2.33447216e-02 -7.86817539e-03 6.26083016e-02
      4.10109349e-02 1.15956627e-02 -1.53822042e-02 -1.73052866e-02
      3.33120138e-03 -2.13435479e-03 -1.80065650e-02 -6.39487570e-03
      5.39354533e-02 1.65514480e-02 -8.06486327e-03 -8.22679419e-03
      -1.16942329e-02 -6.26148609e-03 -1.85368978e-03 -9.65972617e-03
      -2.00333837e-02 2.00065728e-02 1.35829840e-02 -8.95863026e-03
      -3.06868955e-04 -1.08335102e-02 -1.16391722e-02 -5.24385134e-03
      -1.73773784e-02 -3.79822180e-02 4.80190814e-02 2.29884721e-02
      -6.34670956e-03 -1.28550828e-02 -1.96072413e-03 3.88629269e-03
      1.31800929e-02 -1.28889995e-04 -1.56931952e-02 1.66177936e-02
      1.69751327e-02 -2.76973378e-02 -7.67187495e-03 7.65384454e-03
      1.58096720e-02 1.28626563e-02 -3.78416735e-03 -4.05010618e-02
      2.59449407e-02 9.56891850e-03 -3.52896824e-02 1.83074991e-03
      -9.84802935e-03 -9.20621213e-03 -5.39115770e-03 -6.38001505e-03
      -3.45968525e-03 2.47060210e-02 1.89932007e-02 -5.01739569e-02
      1.50560150e-02 1.93270145e-03 -1.04474006e-02 4.69722878e-03
      1.24854296e-02 -1.07960589e-02 -9.09844134e-03 2.07914431e-02
      -4.57395501e-02 -1.92156043e-02 2.20823148e-03 4.69354214e-03
      1.30112460e-02 -2.35760747e-03 -1.49007412e-02 1.06847668e-02
      3.36219519e-02 -2.27035824e-02 6.49931841e-03 1.15570305e-02
      2.60276929e-03 7.33549055e-03 -1.25257811e-02 -2.21278947e-02
      4.24796231e-02 2.19252482e-02 -7.72623997e-03 3.63318287e-02
      1.55314868e-02 -5.11649530e-03 -4.48266137e-03 3.35098687e-03
      -2.62764137e-04 1.07435742e-02 2.48143729e-02 -2.31416151e-02
      -4.83041676e-03 -3.30278766e-03 3.95613955e-03 -1.41088851e-03
      -1.34793418e-02 -9.40483809e-03 3.17618623e-02 3.10433563e-03
      3.29145999e-03 3.50886248e-02 2.78635472e-02 1.20683666e-03
      2.38305097e-03 -2.33455896e-02 -1.31174680e-02 3.74733582e-02
      -2.27803905e-02 -1.01974886e-02 9.89191700e-03 1.07890982e-02
      1.30143901e-03 6.55189343e-03 -9.35875811e-03 2.81907413e-02
      1.77921392e-02 2.61549558e-02 -2.50144936e-02 -3.59199103e-03
      1.10412929e-02 2.50209812e-02 1.60641572e-03 -1.91766173e-02
      -3.74938990e-03 2.36952659e-02 -6.74503902e-03 9.58092045e-03
      2.47075651e-02 3.31442468e-02 2.63696704e-02 -1.56139322e-02
      -1.59188751e-02 -3.06917559e-02 8.01954884e-03 -2.57715918e-02
      8.53287784e-05 2.03496702e-02 1.30715258e-02 1.67883746e-02
      1.27109857e-02 1.79349873e-02 2.74647847e-02 2.15822132e-03
      -3.27871344e-03 3.05738952e-02 5.41937165e-02 3.22014391e-02
      1.50834816e-02 1.21511854e-02 -3.04476060e-02 -1.61909461e-02
      3.07203140e-02 6.94602914e-03 -2.09765290e-04 1.03245946e-02
      1.35794720e-02 -6.02509035e-03 4.12150293e-05 -2.99683977e-02
      -1.23563176e-02 4.30593640e-02 -6.57080486e-03 -1.54292751e-02
      1.46143418e-03 1.21026523e-02 1.18445102e-02 -5.73370839e-03
      -7.90045224e-03 1.98071487e-02 -1.03216956e-03 -4.49040392e-03
      3.94068323e-02 5.05538024e-02 1.23134051e-02 -1.39843989e-02
      -1.50623219e-03 -5.18430509e-02 5.00530517e-03 1.84131728e-03
      1.01085752e-02 4.24917787e-02 7.77604207e-02 4.02535498e-02
      6.64956262e-03 -7.14640971e-03 -1.26010468e-02 8.79764836e-03
      5.69239911e-03 -2.03574095e-02 -2.03581601e-02 1.06751441e-03
      4.70433244e-03 1.66131202e-02 1.04189897e-03 -2.61996407e-02
      -1.98376346e-02 7.78795965e-03 -2.37493571e-02 -9.49411280e-03
      4.39396799e-02 1.73438601e-02 5.93337789e-02 1.56136686e-02
      -2.71094572e-02 -2.73990184e-02 -5.44911157e-03 -2.55956296e-02
      4.72559780e-03 3.25234234e-02 2.80647893e-02 2.46681981e-02
      -1.23073077e-02 -2.63459180e-02 -2.45431475e-02 1.76860001e-02
      9.67605691e-03 -1.32831307e-02 9.71357897e-03 2.60618012e-02
      6.62001669e-02 2.90594064e-02 -1.01471860e-02 -6.27374137e-03
      -7.32462388e-03 -1.63917267e-03 3.11723095e-03 4.86571947e-03
      2.30857427e-03 -1.99349020e-02 3.12025324e-02 5.30244596e-02
      1.04911169e-02 9.19730961e-03 -8.71262047e-03 -1.46455513e-02
      -2.03770585e-02 -3.82039398e-02 -2.90756244e-02 2.46317200e-02
      5.59123419e-02 2.32111141e-02 4.73237131e-03 -2.19009788e-04
      1.31535120e-02 1.78774018e-02 -4.73491527e-04 -4.29942645e-02
      -1.21540474e-02 3.07774469e-02 2.50769742e-02 1.09879728e-02
      -1.99763458e-02 -7.90866744e-03 -3.17013147e-03 -2.21019424e-02
      -1.13923941e-02 -4.25714394e-03 2.87107527e-02 4.59183566e-02
      4.03984152e-02 4.17441353e-02 6.99486863e-03 1.20326206e-02
      -1.10113118e-02 -1.66855082e-02 7.74774118e-04 -2.15349998e-02
      1.72756929e-02 3.42024565e-02 5.13469838e-02 8.57686609e-05
      5.47116483e-03 -6.49321778e-03 -1.48770008e-02 -1.65453162e-02
      -2.39145141e-02 -1.26881870e-02 3.91114764e-02 -4.66536218e-03
      -3.06589995e-02 9.97501705e-03 -2.30889637e-02 2.97507620e-04
      -1.61348411e-03 6.88154600e-04 3.28477882e-02 2.46335417e-02
      -1.18984161e-02 -2.71951463e-02 7.56961899e-03 -3.09669133e-02
      3.33491690e-03 -1.65531319e-03 -7.00308057e-03 3.14619509e-03
      4.26557511e-02 8.74165926e-05 -1.28047531e-02 -8.82709865e-03
      -1.91217735e-02 3.58460797e-03 -5.23096230e-03 -1.21429507e-02
      -1.51462359e-02 2.97147930e-02 2.34392025e-02 9.38824750e-03
      -7.30550755e-03 -2.60524382e-03 2.09552255e-02 1.03994412e-02
      5.35042491e-03 2.20108870e-03 1.11106047e-02 -4.60137464e-02
      -1.79450382e-02 -4.96004196e-03 -1.24214133e-02 1.29732471e-02
      -2.01092893e-03 5.46832336e-03 7.35030603e-03 -7.01061974e-04
      -3.80844846e-02 -1.14504080e-02 7.05533987e-03 6.61246805e-03
      2.73376498e-02 9.03595425e-03 1.77404210e-02 1.01355538e-02
      -5.34656877e-03 1.02957403e-02 -7.24794855e-03 -6.38827030e-03
      1.51998661e-02 1.97043549e-02 1.87094379e-02 1.10669835e-02
      -1.00992573e-02 -1.55407544e-02 7.12858187e-03 -2.36442238e-02
      -9.57712531e-03 2.09058840e-02 2.06151083e-02 2.77426839e-02
      6.54097926e-03 -3.90877873e-02 -4.93106917e-02 -2.72882171e-02
      -7.55968783e-03 1.35865135e-04 4.84341802e-03 4.12211083e-02
      1.96411517e-02 2.44883238e-03 -1.46309249e-02 -4.62542251e-02
      4.71584499e-03 -8.00676085e-03 1.14220288e-02 3.10359169e-02
      4.90097776e-02 2.68629659e-02 4.97056823e-03 -5.83212338e-02
      -1.15915397e-02 2.97522526e-02 -3.36835682e-02 -1.13688838e-02
      1.67317092e-02 8.12845025e-03 1.73208192e-02 4.72848769e-04
      -3.32680307e-02 1.73571520e-02 2.31074076e-02 -8.56554508e-03
      6.34184573e-03 1.24622444e-02 1.45685987e-03 6.15911279e-03
      -1.10448999e-02 -2.72909403e-02 -3.68648842e-02 9.31529969e-04
      -2.56903917e-02 1.61094908e-02 4.89808545e-02 1.05131110e-02
      9.81322769e-03 1.11518474e-02 -5.62069453e-02 -7.85567146e-03
      9.14911740e-03 -1.05523337e-02 1.15100630e-02 2.54852958e-02
      -3.56082269e-03 -8.70196242e-03 -1.44867562e-02 -3.44943181e-02
      1.00946678e-02 -4.74284310e-03 1.91249943e-03 1.90170035e-02
      1.60481222e-02 -1.52858999e-03 -7.33889919e-03 -3.72809283e-02
      -2.03256439e-02 2.60701124e-02 -1.92713700e-02 -2.15271879e-02
      1.15481438e-02 9.35146399e-03 -9.55169462e-03 -2.95695364e-02
      -2.85401549e-02 1.83973517e-02 3.17630246e-02 2.33574174e-02
      1.33637823e-02 2.70272847e-02 3.13581489e-02 -1.21853687e-02
      -2.31451131e-02 -2.09479649e-02 -2.04557870e-02 4.96373735e-02
      2.06638966e-02 3.35160340e-03 3.06749362e-02 2.91476697e-02
      -2.26524100e-02 -4.17606086e-02 -2.11229771e-02 3.02118994e-02
      -7.09284213e-04 -3.64371464e-02 -9.50235222e-03 2.85277907e-02
      -3.45085864e-03 1.13126694e-03 -1.34941312e-02 -1.67941786e-02
      1.07722962e-02 -1.29216788e-02 -4.13429290e-02 -1.41849937e-02
      3.13236192e-02 1.47497235e-02 1.71467743e-03 -4.76981886e-03
      -3.59952562e-02 -1.22855352e-02 2.96751186e-02 -2.05981564e-02
      -2.80475523e-02 2.67347731e-02 4.28908765e-02 1.13009186e-02
      -1.01443706e-02 1.12517020e-02 3.86477374e-02 1.13033820e-02
      -4.69436683e-02 -5.26306368e-02 3.88508774e-02 2.36303266e-02
      3.37840756e-05 1.55113172e-02 2.87743043e-02 3.18959765e-02
      -7.32732762e-04 -4.21397127e-02 -1.05982665e-02 2.69915201e-02
      4.88166185e-03 -1.59925723e-03 1.18431281e-02 -1.76829100e-02
      8.59142002e-03 -1.60381664e-02 -3.94128747e-02 1.78905117e-04
      4.85130660e-02 8.11453722e-03 -5.37893176e-03 3.14558484e-03
      -7.08348770e-03 1.34454237e-03 9.86979436e-03 -6.34424463e-02
      -3.98843624e-02 3.49546596e-02 3.01021822e-02 9.84648336e-03
      3.68861854e-02 4.87415157e-02 2.76755653e-02 -1.29249059e-02
      -5.30815236e-02 -1.06640672e-02 5.19199260e-02 8.55781417e-03
      2.40803491e-02 3.84090170e-02 3.11233271e-02 -1.01683820e-02
      -5.13547659e-03 -3.75326350e-02 -1.31606376e-02 1.72075778e-02
      2.62042247e-02 1.19082360e-02 -1.68895125e-02 -1.47644123e-02
      -3.10094692e-02 5.31923724e-03 -1.15971230e-02 -3.38414684e-02
      -2.86384556e-03 2.72597559e-02 4.93610837e-02 1.97557453e-02
      -4.25758306e-04 -9.56955645e-03 -4.98459581e-03 -1.33735631e-02
      -1.62807424e-02 4.27007936e-02 2.75071654e-02 1.73846409e-02
      -2.74130492e-03 7.29058264e-03 -2.51470804e-02 4.97069769e-03
      -2.13687606e-02 -3.32753658e-02 8.56380444e-03 2.36453582e-02
      4.15350497e-02 2.55645383e-02 1.70615185e-02 -1.71767976e-02</_></support_vectors>
  <decision_functions>
    <_>
      <sv_count>1</sv_count>
      <rho>3.6120203864614560e+00</rho>
      <alpha>
        1.</alpha>
      <index>
        0</index></_></decision_functions></my_svm>
</opencv_storage>
