<?xml version="1.0"?>
<opencv_storage>
<my_svm type_id="opencv-ml-svm">
  <svm_type>C_SVC</svm_type>
  <kernel><type>LINEAR</type></kernel>
  <C>1.0000000000000001e-01</C>
  <term_criteria><epsilon>1.1920928955078125e-07</epsilon>
    <iterations>1000</iterations></term_criteria>
  <var_all>2916</var_all>
  <var_count>2916</var_count>
  <class_count>2</class_count>
  <class_labels type_id="opencv-matrix">
    <rows>1</rows>
    <cols>2</cols>
    <dt>i</dt>
    <data>
      1 2</data></class_labels>
  <sv_total>1</sv_total>
  <support_vectors>
    <_>
      -1.41234149e-03 -1.10189775e-02 -4.45964420e-03 2.48481822e-03
      7.57828215e-03 2.32491158e-02 1.57948341e-02 4.84732795e-04
      5.93427802e-03 -2.37602536e-02 -1.58367269e-02 2.81042513e-02
      2.75412165e-02 3.15993913e-02 1.63418185e-02 1.05271665e-02
      -7.66962441e-03 8.07502482e-04 1.16122058e-02 -3.00121661e-02
      -1.54239060e-02 2.55476516e-02 5.64682181e-04 1.52980853e-02
      1.00366147e-02 -4.86564916e-03 -6.74906978e-03 -5.40267006e-02
      -1.34354541e-02 1.88088417e-02 4.18445021e-02 2.61864010e-02
      8.63336585e-03 9.26121511e-03 -3.65192979e-03 -1.54851535e-02
      -8.82241409e-03 1.94618874e-03 8.13659932e-03 4.96339379e-03
      1.49251362e-02 3.03410366e-03 2.64804810e-03 -7.41417194e-03
      6.32010773e-03 1.78756323e-02 6.11837581e-03 5.20089781e-03
      -9.62274149e-03 1.34758595e-02 7.45107699e-03 4.02873242e-03
      -4.16818587e-03 2.43236474e-03 -2.72525847e-02 -1.92361400e-02
      2.43746359e-02 1.89210121e-02 9.11100302e-03 -6.83338149e-04
      7.81547185e-03 -6.38425350e-03 -9.06434376e-03 9.80870519e-03
      8.24590307e-03 7.07823783e-03 3.18321772e-03 1.34012699e-02
      2.07823189e-03 8.17988347e-03 -6.43977104e-03 -4.36757598e-03
      6.53104950e-03 9.60965117e-05 3.76535347e-04 -6.11124188e-03
      7.68753421e-03 4.33818717e-03 3.87732685e-03 -1.45087135e-03
      1.63025837e-02 -1.70650091e-02 -5.07231383e-03 -1.88988366e-03
      -9.16727260e-03 1.10964226e-02 1.94530608e-03 1.14236102e-02
      1.01889968e-02 2.72730067e-02 6.71000686e-03 5.14537469e-03
      -7.11236848e-03 -4.51329816e-03 -3.25943297e-03 -2.09961226e-03
      -7.58558046e-03 -2.30483292e-03 7.40568340e-03 -7.67583074e-03
      -3.37903132e-03 -4.87287389e-03 -7.69428676e-03 -9.93025675e-03
      -1.27105750e-02 -1.38016585e-02 8.91195331e-03 8.98799114e-03
      -1.57676768e-02 -2.16180008e-04 -1.25238718e-03 -4.75957803e-03
      7.50610325e-03 -2.40390582e-04 2.71528075e-03 9.56412591e-03
      3.57803293e-02 -1.39666470e-02 1.16068646e-02 7.50141777e-03
      -1.03453798e-02 1.78199634e-02 3.23066511e-03 -9.80253564e-04
      8.23176652e-03 3.10722757e-02 -8.49185325e-03 -2.31219805e-03
      -8.02673399e-03 -9.63906664e-03 -6.87438343e-03 -6.16644451e-04
      -1.76649378e-03 8.24669003e-03 1.42641850e-02 -9.17630829e-03
      -2.27084570e-02 -1.33470967e-02 -1.81219950e-02 -1.97338435e-04
      3.25497705e-03 -1.82809192e-03 8.22140928e-03 3.28710838e-03
      1.18144741e-03 2.92313565e-03 4.58534248e-03 -3.46813560e-03
      8.85359012e-03 -8.02227471e-04 -2.82720686e-03 3.21892579e-03
      1.14044324e-02 3.38092186e-02 9.14127287e-03 -5.33579092e-04
      -6.12452254e-03 3.12474486e-03 -3.85267637e-03 -2.77172192e-03
      8.32214486e-03 -1.28888674e-02 7.24109542e-03 -2.04105973e-02
      1.31386938e-03 -1.61674689e-03 -3.66869289e-03 -2.93082022e-03
      -3.54506541e-03 -2.90739350e-03 -2.63522589e-03 7.08535407e-03
      -1.97805371e-02 -6.09024311e-04 -3.32315941e-03 -4.48637921e-03
      -5.30674728e-03 -6.32791128e-03 -1.04242535e-02 1.16527127e-02
      1.06532499e-02 8.53404868e-03 -7.32451165e-03 -6.40813122e-03
      -3.42507585e-04 -1.50848227e-03 4.42850898e-04 1.11949760e-02
      -6.71878224e-03 1.81238875e-02 1.18209992e-03 -8.66717100e-03
      -4.09488846e-03 3.71885108e-05 -1.82193052e-03 -2.85899616e-03
      7.10887928e-03 1.04361097e-03 -6.62877876e-03 -2.00957078e-02
      -4.58650850e-03 -5.47850225e-03 -5.88020077e-03 -1.38351368e-02
      -1.58790126e-02 -1.00020189e-02 1.00235716e-02 1.71097592e-02
      -2.74641700e-02 -6.35608146e-03 -1.27582652e-02 -9.76866856e-03
      -1.80998892e-02 -1.83723457e-02 -7.30116852e-03 2.34417450e-02
      1.57435704e-02 -6.66112220e-03 -1.29684317e-03 6.17755053e-04
      8.61753797e-05 -3.73783085e-04 -5.31111052e-03 1.26250365e-04
      -1.39381327e-02 2.94100381e-02 3.15954280e-03 4.24301485e-03
      7.35393353e-03 8.21857341e-03 3.85374415e-06 -1.14347767e-02
      -5.01145516e-03 -2.71928720e-02 3.10503151e-02 -1.40777612e-02
      -1.29046559e-03 -8.19761585e-03 -5.71785914e-03 -6.74784556e-03
      -1.23893004e-02 -7.62735819e-03 -4.12496040e-03 1.78707317e-02
      6.04245765e-03 1.99708599e-03 2.24256841e-03 8.75177793e-04
      -2.73220520e-03 -2.26872116e-02 -3.75292152e-02 3.44858854e-03
      1.59044620e-02 1.62890851e-02 4.12588101e-03 1.07744876e-02
      1.88331008e-02 5.46529703e-03 -1.90615805e-03 -4.68913419e-03
      -2.65229978e-02 -1.40192278e-03 1.40929148e-02 -2.85107526e-03
      3.64845688e-03 1.04202954e-02 -3.57474724e-04 5.96913509e-03
      -8.31729826e-03 -9.84874833e-03 7.10731512e-03 1.85764041e-02
      5.58398850e-03 3.32478131e-03 6.45555847e-04 6.52308809e-04
      -7.20050605e-03 6.22215273e-04 -7.72885373e-03 -5.82940644e-03
      -1.60218996e-03 -8.59025773e-03 -1.32496059e-02 -6.04988867e-03
      1.05274580e-02 1.32420175e-02 3.65023059e-03 -3.66410310e-03
      8.35727341e-03 6.66892529e-03 4.48050257e-03 1.41118448e-02
      1.59019567e-02 -2.15542410e-03 -9.28037241e-03 -2.30105370e-02
      -9.23633669e-03 1.15791860e-03 9.28001537e-04 -1.98317855e-03
      2.33956277e-02 3.15155871e-02 1.89357419e-02 -1.26139792e-02
      -8.46835971e-03 -2.56726728e-03 -9.13165975e-03 5.43170841e-04
      -9.32673272e-03 -9.14473645e-03 5.30456379e-03 1.99394692e-02
      1.11785587e-02 -2.16592848e-02 -2.18794979e-02 -5.88302547e-03
      -9.70770838e-04 -1.09668486e-02 -1.13333249e-02 2.39498150e-02
      2.55144406e-02 -3.21381958e-03 -2.42361091e-02 -1.53627270e-03
      -4.69101360e-04 -5.79776301e-04 -3.10579641e-03 2.37980951e-02
      1.98207796e-04 7.65608624e-04 -2.05189199e-03 -6.82367245e-03
      -1.23716453e-02 -1.51192946e-02 -1.82384476e-02 2.20610742e-02
      2.60962937e-02 1.79317147e-02 6.00971340e-04 3.49353137e-03
      2.90491153e-03 -2.71510542e-03 -1.99616328e-02 3.70698585e-03
      -2.27401266e-03 1.67679563e-02 1.14409383e-02 -4.00369661e-03
      9.80552752e-03 -4.30399040e-03 -1.76332854e-02 -1.09926043e-02
      -1.57499984e-02 4.71791998e-03 3.23719159e-02 3.84867564e-02
      9.74281784e-03 4.59619844e-03 8.91919620e-03 4.63276356e-03
      -1.93646718e-02 -1.79810487e-02 -3.08347982e-04 1.24053089e-02
      7.74956308e-03 -2.04408250e-04 2.61881948e-03 -6.69511780e-03
      6.73970673e-04 2.19563977e-03 2.30055404e-04 -2.37038868e-04
      7.60596618e-03 1.13846539e-02 3.39144492e-03 -4.78821865e-04
      -1.13370903e-02 -2.80759833e-03 -6.41649822e-03 -2.15658043e-02
      -2.82369554e-02 4.41807695e-03 2.13510469e-02 9.00282245e-03
      9.10547096e-03 -3.53203766e-04 4.80031362e-03 -1.23274419e-02
      -1.63192805e-02 -2.42525991e-02 5.86486561e-03 6.90610241e-03
      1.73103344e-02 2.19538063e-03 9.02632996e-03 8.52937251e-03
      -3.26683861e-03 1.35260285e-03 -3.88391875e-03 1.21889287e-03
      -2.49803113e-03 -3.48506682e-03 -6.53366558e-03 4.94066393e-03
      2.81832251e-03 1.42838305e-03 -1.14775291e-02 -6.56836433e-03
      -5.31152869e-03 -1.19327446e-02 -1.71873178e-02 -1.43248923e-02
      1.33573320e-02 2.33381055e-02 5.98361483e-03 -2.11331584e-02
      -1.23269614e-02 -3.14318947e-03 2.40061292e-03 -4.77543520e-03
      2.74539227e-04 1.66697484e-02 1.94898155e-02 1.31881721e-02
      -3.85664478e-02 -1.82043165e-02 -1.69179942e-02 -1.74085088e-02
      -2.10932791e-02 -1.92086808e-02 1.86288562e-02 2.91957706e-02
      -1.75508019e-03 -2.82142521e-03 -4.13566083e-03 -3.73751600e-03
      -7.99285900e-03 -4.75501176e-03 -3.82400933e-03 -6.96055172e-03
      2.78580207e-02 1.86164919e-02 -5.12204226e-03 -1.40577890e-02
      -1.43049229e-02 -1.61099173e-02 -7.80407107e-03 -8.76788888e-03
      -1.51870456e-02 1.69456657e-02 3.37052941e-02 -8.56027286e-03
      -1.21650565e-02 -1.12911435e-02 -2.08302066e-02 -2.39040516e-02
      -7.17581017e-03 -1.68165080e-02 4.44927365e-02 4.37077470e-02
      -3.10431398e-03 -3.77650931e-02 -2.35245805e-02 -3.20652351e-02
      -2.67067552e-02 -4.80295252e-03 -1.60834771e-02 1.79355331e-02
      1.41888475e-02 -4.66829719e-04 -5.69934910e-03 -3.82479746e-03
      -7.94206746e-03 -6.32343348e-03 -2.75981962e-03 -5.42898546e-04
      1.15457841e-03 1.08965700e-02 -9.59511846e-03 -3.09254718e-03
      -3.73527757e-03 -1.17788212e-02 -8.16367846e-03 -4.75741969e-03
      -3.15966969e-03 5.36327204e-03 4.83941007e-03 2.33395910e-03
      -2.48791762e-02 -7.30796531e-03 -2.42742598e-02 -1.27541926e-02
      3.73183796e-03 2.25611236e-02 7.44702667e-03 -9.25514323e-04
      1.15699666e-02 -7.70499511e-03 -1.95944048e-02 -2.71571111e-02
      -1.54831670e-02 6.85243122e-03 2.86615826e-02 1.24429818e-02
      -3.23106855e-04 -1.33001572e-02 -4.86848527e-04 -4.81494749e-03
      -1.87232662e-02 -1.16014378e-02 -1.16698043e-02 -9.76282987e-04
      1.41096897e-02 1.87140517e-02 -1.72765292e-02 -2.36910791e-03
      -9.27965529e-03 -2.09066831e-02 -1.65216215e-02 -7.77762849e-03
      2.80981720e-03 3.33819427e-02 4.76680184e-03 1.75716981e-04
      7.52902171e-03 -1.74095333e-02 -3.04214582e-02 -1.61029696e-02
      -6.60464168e-03 1.37202190e-02 5.09492354e-03 2.62073856e-02
      -6.94137113e-03 4.81653819e-03 -1.76180284e-02 -2.88269259e-02
      -1.11670513e-02 -8.58538691e-03 -2.24762387e-03 3.18513997e-02
      3.19080390e-02 -1.01064108e-02 -2.50239461e-03 -9.37930588e-03
      -1.09920306e-02 -6.48643170e-03 -7.33063603e-03 -5.37580857e-03
      3.67176253e-03 1.67985018e-02 -7.27295829e-03 -4.51005157e-03
      -9.26412176e-03 -6.59540668e-03 -3.71439848e-03 -1.21454438e-02
      -1.75119787e-02 1.21660810e-02 3.55094969e-02 -1.99146755e-02
      -1.13354865e-02 -2.50744186e-02 -2.12956555e-02 -4.87774052e-03
      -9.97544080e-03 -7.63098896e-03 2.64753271e-02 2.82758437e-02
      -1.15133980e-02 -1.89807080e-02 -3.31243128e-02 -2.08620224e-02
      -1.74439866e-02 -1.52316280e-02 -1.16556259e-02 2.92448662e-02
      1.05225910e-02 -2.65616662e-04 -5.36515028e-04 -6.05756976e-03
      -3.48976674e-03 -1.14156283e-03 4.53013839e-04 5.20657888e-03
      9.04269330e-03 2.20239582e-03 -8.58343858e-03 -1.44763561e-02
      -1.94429476e-02 -1.41439959e-02 1.18823322e-02 2.05625966e-02
      2.09846329e-02 -4.88968100e-03 -3.86199681e-04 -7.33363209e-03
      -1.94603216e-03 -1.25259589e-02 -4.88417968e-03 -7.06194527e-03
      2.61059916e-03 8.99912324e-03 1.05655547e-02 -2.25369111e-02
      -1.74138304e-02 -5.69602475e-03 -1.06470520e-02 -3.91023787e-04
      1.90064944e-02 1.70406122e-02 -5.64842531e-03 8.35085660e-03
      -8.42699781e-03 -3.61440121e-03 -1.70442108e-02 -1.18352575e-02
      -3.94756021e-03 2.55740546e-02 8.85723345e-03 -1.18807694e-02
      -1.31602830e-03 -1.34798069e-03 -2.24383082e-03 -1.54964132e-02
      -3.74010089e-03 1.07689872e-02 2.90912259e-02 -1.25067728e-03
      -1.61384232e-02 -1.52072439e-03 -1.41275825e-03 -2.04825941e-02
      1.48484111e-03 7.38431793e-03 8.13140627e-03 4.24759742e-03
      1.45732397e-02 -1.67634040e-02 -9.56851710e-03 -7.91559834e-03
      -2.30965614e-02 -3.97099694e-03 1.98757108e-02 1.81505922e-02
      7.46182573e-04 4.84204991e-03 -9.30659007e-03 -5.60924038e-03
      -2.41608676e-02 -4.30039596e-03 -9.06744754e-06 7.70785520e-03
      1.42427282e-02 1.93030038e-03 2.08718665e-02 4.25675791e-03
      -3.62008973e-03 -1.40581951e-02 -1.04717212e-02 -9.28700808e-03
      8.66645295e-03 3.86909395e-02 2.09694058e-02 1.99994631e-02
      8.11119843e-03 1.12875625e-02 -2.21262872e-02 -2.35201214e-02
      -1.08302720e-02 -6.01531845e-03 1.23302070e-02 7.66275218e-03
      1.99361183e-02 6.34241290e-03 -4.68336511e-03 8.44660401e-03
      -7.30043370e-03 -7.63831055e-03 4.15322045e-03 1.62362517e-03
      1.12472791e-02 3.18377800e-02 2.34484002e-02 1.43714957e-02
      -1.01716835e-02 -1.12760812e-02 -1.27228163e-02 3.92727368e-03
      1.94136333e-02 8.38303007e-03 1.18008442e-02 2.44327146e-03
      -2.35691504e-03 1.80509202e-02 -1.13602811e-02 -1.36927823e-02
      -4.69695404e-03 8.77394620e-03 1.00918757e-02 7.27394689e-03
      1.45810926e-02 1.20339068e-02 1.60591304e-02 -9.99433454e-03
      -1.11168008e-02 -1.06060524e-02 -1.36924488e-02 -1.93235974e-04
      1.08834393e-02 1.30609162e-02 1.49161881e-02 4.67872694e-02
      2.50873342e-02 -2.74485853e-02 -1.34324422e-02 -3.09844455e-03
      -1.11498404e-02 -5.97391324e-03 -8.17213580e-03 2.02818252e-02
      3.47693861e-02 -1.09385792e-02 -8.97431560e-03 -7.35560525e-03
      -3.19023849e-04 -7.38484832e-03 -5.55188768e-03 -1.15672117e-02
      1.59867853e-02 3.60318162e-02 -2.12147180e-02 -1.46169402e-02
      -3.40110734e-02 -1.11252600e-02 -1.34331034e-02 -1.79711971e-02
      -1.31416544e-02 3.07313837e-02 6.71469048e-02 1.83595605e-02
      -2.01454647e-02 -1.69638358e-02 5.84692927e-04 -1.10983886e-02
      -2.61750109e-02 -5.27733937e-02 -5.93076879e-03 5.93569092e-02
      -2.27140915e-03 -1.75943244e-02 -2.99359187e-02 -8.48601200e-03
      8.81407037e-03 -1.74781196e-02 -9.94777214e-03 1.22773414e-02
      3.15827802e-02 -7.12598115e-03 -2.13779900e-02 -2.28012465e-02
      -1.36463419e-02 -8.91432259e-03 -5.09872288e-03 9.68376826e-03
      4.11421731e-02 3.91725041e-02 -1.04995435e-02 -2.92695053e-02
      -1.73652600e-02 -3.97647545e-02 -2.28851084e-02 1.08044371e-02
      1.09197544e-02 9.58821829e-03 1.21730464e-02 -3.19331861e-03
      -1.38417194e-02 -3.48933265e-02 -2.12040800e-03 -4.85571893e-03
      3.22531834e-02 2.65258178e-02 2.72108354e-02 -3.67712532e-03
      -3.70059605e-03 -5.54963714e-03 -4.04128293e-03 -2.37727482e-02
      7.10452441e-03 4.74717915e-02 5.53732365e-02 -7.28218537e-03
      -1.17297960e-03 6.54010521e-03 -1.19873974e-02 -2.45141354e-03
      -2.76080854e-02 -5.46033680e-03 2.64318902e-02 2.65005399e-02
      8.63947440e-03 -3.29057151e-03 1.44046554e-02 3.15817306e-03
      -1.62047204e-02 -1.64434109e-02 4.31712111e-03 1.72477067e-02
      1.95040908e-02 -1.35010965e-02 -4.08736728e-02 1.40869226e-02
      5.84521377e-03 1.45612145e-02 -1.16128530e-02 1.10233696e-02
      5.47785945e-02 2.70744152e-02 -2.05528159e-02 -4.41581532e-02
      3.29480805e-02 4.05877344e-02 3.98796201e-02 -2.20539351e-03
      2.20452566e-02 2.48213429e-02 -1.08199958e-02 -3.49717140e-02
      -1.27215739e-02 7.55839609e-03 1.01425499e-02 -9.04084090e-03
      -2.23650616e-02 -3.46579030e-03 -1.97949383e-04 1.05636073e-02
      -1.21042198e-02 4.27304097e-02 1.77200343e-02 9.39684827e-03
      -6.26528542e-03 -2.57491246e-02 -1.19686069e-03 -4.78210300e-03
      3.77744297e-03 8.93273670e-03 -2.98263151e-02 3.99481356e-02
      4.02588956e-02 1.48301031e-02 3.69203719e-03 -3.95312067e-03
      -6.26997231e-03 -2.66140397e-03 -3.88806276e-02 2.08212119e-02
      5.37455082e-02 3.25378105e-02 1.06184995e-02 6.02862972e-04
      -7.96838664e-03 -9.00216587e-03 -7.34662171e-03 -7.12519931e-03
      2.83153206e-02 -3.32757970e-03 -1.61512871e-03 -2.07838062e-02
      -1.42929740e-02 -5.28984936e-03 -5.68228262e-03 -6.54580537e-03
      1.75904278e-02 5.01923151e-02 3.84319178e-03 -5.57313068e-03
      -1.32063907e-02 -8.83481931e-03 -1.72570460e-02 -1.83172934e-02
      -1.91058330e-02 3.05676162e-02 3.38685662e-02 1.49669787e-02
      6.99939951e-03 -1.03195962e-02 -1.56655740e-02 -1.89485755e-02
      -2.34360043e-02 -2.15161312e-02 2.24033464e-02 2.67600603e-02
      -1.41725095e-03 -4.97556338e-03 -3.76102142e-03 -7.02926330e-03
      -2.48467792e-02 -4.11802679e-02 -2.94154249e-02 2.43503768e-02
      7.07203150e-03 -2.68954970e-03 4.27235616e-03 -5.06338256e-04
      -6.67459699e-06 -3.65722296e-03 -4.33170795e-03 -7.43077835e-03
      1.81942508e-02 -9.24839918e-03 -1.42816128e-02 9.99143347e-03
      1.14220474e-02 -7.45400228e-03 -4.16341558e-04 7.55927153e-03
      -2.14343928e-02 2.78569721e-02 5.13843168e-03 1.43764792e-02
      5.27421245e-03 -2.56315991e-03 -5.75774396e-03 -1.88521892e-02
      -2.62086242e-02 -9.41633806e-03 2.03129556e-02 1.21921515e-02
      1.07626030e-02 2.68282946e-02 1.44142285e-02 -8.12554546e-03
      -1.29281264e-02 -2.13361811e-02 -1.98565219e-02 1.99275576e-02
      3.02655390e-03 -1.22810509e-02 2.04512030e-02 4.08872589e-02
      -6.16940018e-03 1.90466293e-03 4.79596696e-04 -1.19189220e-02
      -6.43315725e-04 -1.43820196e-02 -1.61261298e-02 1.54502159e-02
      3.29217240e-02 1.27239935e-02 -3.36881168e-03 -4.30866191e-03
      -1.07521506e-03 -5.18980576e-03 -5.86633896e-03 2.11968403e-02
      3.83224338e-02 4.26780209e-02 -1.69700645e-02 -1.62279736e-02
      -1.48333358e-02 -2.04973649e-02 5.31545980e-03 -1.96399968e-02
      -2.90240557e-03 2.45750844e-02 3.63622978e-02 1.69508643e-02
      -1.21036004e-02 -5.07482374e-03 -5.70412120e-03 -2.17857715e-02
      -4.09808848e-03 -3.00722849e-02 -6.41493080e-03 3.14552919e-03
      5.32252947e-03 4.01772605e-03 2.64630802e-02 1.04816500e-02
      -3.54411174e-03 1.35356085e-02 -6.81058830e-03 2.71637272e-03
      -4.87721059e-04 -3.31775611e-03 1.90644376e-02 3.36849168e-02
      8.21840297e-03 1.75369866e-02 -1.21479388e-02 -3.57715599e-02
      -1.80682875e-02 1.60850342e-02 -3.66690173e-03 -4.33590403e-03
      2.29958035e-02 1.90334581e-02 1.67748693e-03 2.60476526e-02
      5.99836698e-04 1.05336048e-02 1.69044621e-02 -7.93741457e-03
      1.54289501e-02 3.73122990e-02 3.45640816e-02 1.07846223e-02
      2.50538755e-02 4.84195445e-03 -4.39479016e-03 -9.90134478e-03
      -1.25989495e-02 3.43977008e-03 4.47478285e-03 1.59601513e-02
      3.14759575e-02 6.74321651e-02 4.59607877e-02 -2.16273107e-02
      -2.02508960e-02 -9.39294137e-03 1.32583536e-03 2.66893837e-03
      -2.53368281e-02 2.29393505e-02 2.22029835e-02 1.20168021e-02
      1.45201916e-02 -1.65812280e-02 -1.90487206e-02 -1.00598659e-03
      1.07779866e-02 1.55444974e-02 1.87310986e-02 2.81722955e-02
      4.01833802e-02 -4.19905595e-03 -2.91852131e-02 -4.15386120e-03
      4.19609249e-03 2.48007732e-03 -1.26751671e-02 -7.37508293e-03
      7.55060464e-02 2.53176615e-02 -1.87268034e-02 -1.03041893e-02
      2.28825770e-03 -3.83483153e-03 -1.28324609e-02 -4.78075221e-02
      -6.87666051e-03 5.37579060e-02 6.13688258e-03 -8.62296857e-03
      -1.95503496e-02 1.53082553e-02 1.80744883e-02 -1.58712752e-02
      -8.66747636e-04 3.17233428e-02 3.53426635e-02 1.70465168e-02
      -1.11518037e-02 -9.06137226e-04 -3.23406013e-04 -4.27947566e-03
      -8.88099987e-03 -3.87183614e-02 -3.00963931e-02 3.87964547e-02
      1.29862828e-02 2.63384916e-03 -6.37482852e-03 9.76846833e-03
      -1.57089867e-02 -1.03287902e-02 -2.96702539e-03 1.23125892e-02
      6.08275086e-03 4.07494279e-03 6.62495149e-03 -1.20314322e-02
      9.12867673e-03 1.34377452e-02 9.07688215e-03 1.17068868e-02
      2.50167469e-03 -8.96233041e-03 2.81288452e-03 8.29576328e-03
      5.03685849e-04 -1.47720454e-02 1.29353069e-02 3.81666496e-02
      3.10944337e-02 -1.68171413e-02 -8.95777624e-03 5.19995847e-05
      2.31244322e-03 -8.75369366e-03 2.33784374e-02 7.59668229e-03
      9.74665303e-03 3.17441812e-03 -1.81346741e-02 -3.18019763e-02
      -2.55949865e-03 -6.93545770e-03 1.46758975e-02 4.53501344e-02
      1.31095806e-03 1.72831416e-02 -1.69569999e-02 -4.95478772e-02
      -3.02681476e-02 2.39156978e-03 9.02077835e-03 2.69094259e-02
      6.11796370e-03 2.73599308e-02 2.24928036e-02 -7.39313662e-03
      -3.56355458e-02 -3.86964492e-02 1.93465259e-02 5.55430278e-02
      3.39319669e-02 1.04573080e-02 1.69753451e-02 -2.05002222e-02
      -1.88243128e-02 -3.10521182e-02 -2.32252702e-02 -1.16197970e-02
      -3.90378805e-03 2.35694982e-02 5.24628311e-02 4.36590612e-02
      -7.20799714e-03 -2.68857386e-02 -4.17392366e-02 -2.44315248e-02
      8.67558829e-03 3.29187997e-02 3.43933739e-02 4.06670496e-02
      2.56332364e-02 -3.80585194e-02 -3.69568132e-02 -4.25859243e-02
      -2.30135154e-02 2.58966926e-02 2.62466520e-02 1.99567224e-03
      1.39908260e-02 -1.03297513e-02 -2.59964634e-02 -6.44442951e-03
      -2.71655321e-02 7.89414393e-04 2.66850423e-02 2.57892180e-02
      2.68445853e-02 1.44923460e-02 -1.30211599e-02 -1.76140349e-02
      3.83999990e-03 -1.71545018e-02 -6.47158548e-03 3.83299440e-02
      3.17696780e-02 2.24848948e-02 1.55928247e-02 -7.59794144e-03
      -4.37164530e-02 -9.91680846e-03 -3.36198620e-02 1.80222280e-02
      3.61849591e-02 2.58229896e-02 1.11890305e-02 3.13543133e-03
      -2.16705780e-02 -2.18020901e-02 6.64612604e-03 -1.95660386e-02
      3.12828310e-02 1.67923383e-02 1.40174124e-02 1.00269848e-02
      4.13993420e-03 -1.60129741e-02 -2.85001658e-02 -1.21258786e-02
      1.76397990e-02 2.11090967e-02 1.84149842e-03 -4.94854685e-05
      6.64866250e-03 -6.62706746e-03 -2.22865082e-02 -3.56256068e-02
      3.34562664e-03 2.74584200e-02 1.44872218e-02 1.42008318e-02
      2.02904157e-02 -1.32523372e-03 -3.89066641e-03 -2.50108540e-02
      -1.86308026e-02 4.40814253e-03 9.91920196e-03 -1.28449863e-02
      1.24255028e-02 1.58880427e-02 5.49392635e-03 -1.17801055e-02
      -2.17870921e-02 -2.88708415e-02 -9.63673345e-04 1.26961730e-02
      -5.57656959e-03 3.17111099e-03 -3.46738286e-03 -2.23886757e-03
      -7.96101429e-03 -1.57736484e-02 -1.20423557e-02 1.53556578e-02
      3.24830227e-02 1.06757758e-02 1.42784957e-02 2.43046340e-02
      1.05292238e-02 -1.64384712e-02 -1.11651272e-02 -1.31887682e-02
      1.37179298e-03 3.17153670e-02 -1.77666824e-02 9.10599157e-03
      -5.48360450e-03 -4.96682012e-03 -2.52722986e-02 -1.99505202e-02
      -8.08807369e-03 9.37394518e-03 3.65596265e-02 1.69459288e-03
      1.50979878e-02 3.82024911e-03 6.48303470e-03 -1.74907222e-02
      -2.10778438e-03 -9.36444104e-03 -2.74573849e-03 5.10534495e-02
      -9.13487561e-03 2.44261585e-02 4.25867550e-02 2.78557464e-02
      -1.76628344e-02 -1.44982319e-02 -1.71771701e-02 -1.33165643e-02
      4.49161837e-03 -1.42818941e-02 1.82717829e-03 1.17559172e-02
      3.11794914e-02 2.24872828e-02 5.67217963e-03 1.70288177e-03
      -3.03932745e-03 -2.14420650e-02 -6.27988111e-03 4.53022355e-03
      2.86402311e-02 2.00776849e-02 -2.93736104e-02 -1.55932028e-02
      -8.59955885e-03 -6.60636183e-03 -4.79872280e-04 -1.57932024e-02
      -3.32337175e-03 8.84151366e-03 3.04926131e-02 8.74163862e-03
      7.58651877e-03 -8.13441724e-03 -6.50779018e-03 -6.56248722e-03
      -4.23818390e-04 -9.09731537e-03 -1.20308539e-02 5.74249076e-03
      -2.29083467e-02 -3.52760800e-03 9.96635761e-03 1.02824792e-02
      1.45914024e-02 1.29264211e-02 -1.71812507e-03 1.01813478e-02
      1.68658476e-02 -1.85176805e-02 3.53743322e-03 3.19119543e-02
      1.61601510e-02 9.49118473e-03 1.14102121e-02 6.78691873e-03
      -4.98002279e-04 1.85862817e-02 -2.04929858e-02 -1.86600592e-02
      7.20791891e-03 -1.26914273e-03 1.08317146e-03 3.41847399e-03
      1.56668350e-02 -8.00961745e-04 1.07257618e-02 -2.03313231e-02
      1.79099583e-03 3.09484098e-02 8.86745472e-03 2.26423168e-03
      6.79897005e-03 1.40706738e-02 2.58858781e-02 4.00994811e-03
      -1.39502604e-02 7.06650876e-03 9.46210884e-03 5.54507924e-03
      3.10929073e-03 -8.28931015e-03 3.01164836e-02 2.15020310e-02
      5.29609108e-03 8.69626831e-03 1.03281774e-02 3.22004454e-03
      -1.58167724e-02 -1.25164744e-02 -2.34406386e-02 -1.44427884e-02
      8.93761683e-03 2.60234363e-02 2.02154629e-02 5.58303064e-03
      1.99858379e-02 1.85337011e-03 -1.40200816e-02 -4.21594717e-02
      -1.44067444e-02 1.99145600e-02 3.92129309e-02 2.93303356e-02
      1.28218839e-02 3.87332519e-03 2.87534632e-02 -1.00845518e-02
      6.77380385e-03 1.31553197e-02 1.14736918e-04 4.32325248e-03
      -5.03506558e-03 -1.83078814e-02 -1.01584736e-02 -8.72896798e-03
      -9.89154726e-03 1.75728798e-02 1.66116823e-02 4.35330067e-03
      1.67244337e-02 1.82563681e-02 -1.45837925e-02 -2.14575464e-03
      2.44958745e-03 -2.64176424e-03 -2.87145749e-02 -3.03738955e-02
      -7.62697755e-06 2.07632370e-02 7.84389768e-03 -1.69173405e-02
      -9.61441174e-03 3.51484120e-02 2.09502988e-02 9.41557437e-03
      -1.10727148e-02 -2.79339850e-02 1.21876011e-02 2.06664111e-02
      -2.36499943e-02 -7.58764148e-03 1.09612653e-02 2.35237759e-02
      -1.37667852e-02 -5.36809862e-03 -5.05928416e-03 -8.07807967e-03
      3.67059372e-02 -6.14913646e-04 -5.13951154e-03 -3.24984081e-03
      -1.54022481e-02 -3.07945795e-02 -4.88706212e-03 -1.73380226e-02
      2.65174136e-02 7.69623071e-02 2.33085938e-02 -6.75760384e-05
      -2.20349841e-02 -4.00887355e-02 -1.98219437e-02 -1.22836260e-02
      -1.53466612e-02 -2.90302490e-03 4.20021266e-02 -1.00481929e-02
      -1.64830852e-02 -1.29708240e-03 -1.12582473e-02 -5.30021451e-02
      -3.59170251e-02 -1.06961112e-02 6.79666251e-02 6.40318394e-02
      -3.35540366e-03 -2.55675856e-02 -8.75247922e-03 -2.20674723e-02
      -1.22694969e-02 -1.20989429e-02 -1.51810171e-02 1.48059465e-02
      6.75236061e-02 2.20123492e-02 -1.93884559e-02 -1.99265499e-02
      -2.57238653e-02 -2.34879795e-02 -1.41807711e-02 -8.46535526e-03
      2.61998232e-02 4.21483628e-02 1.48324855e-02 -2.22545620e-02
      -2.28383262e-02 -2.70489063e-02 -3.36357355e-02 -3.04396171e-02
      -3.46391089e-02 4.16135117e-02 6.42152131e-02 8.04745406e-03
      -1.63957160e-02 -9.11368430e-03 -2.42366940e-02 -2.08132118e-02
      -1.86713543e-02 -4.28501032e-02 2.13456061e-02 3.52963358e-02
      4.46247533e-02 2.32553040e-03 -3.93373985e-03 -2.59517264e-02
      -2.19211243e-02 1.02979438e-02 1.13806659e-02 1.16292676e-02
      2.22600102e-02 1.56396721e-03 -2.26061102e-02 1.96255441e-03
      -2.40518227e-02 -1.03129372e-02 2.43595187e-02 1.08537162e-02
      1.10441549e-02 1.69039275e-02 -2.98652449e-03 -1.18825817e-02
      1.74057540e-02 -1.50518762e-02 -2.32398249e-02 -9.62827448e-03
      -2.14679390e-02 -9.99453571e-03 2.18043160e-02 3.16001214e-02
      3.91858746e-04 1.96685623e-02 -2.74902955e-02 -5.37924469e-03
      1.43055581e-02 7.85661582e-03 2.02170620e-03 3.60052027e-02
      3.04168724e-02 1.81455165e-02 2.48643477e-02 -1.02753267e-02
      -7.42053380e-03 7.61147263e-03 -4.22149105e-03 -9.81207006e-03
      1.79106724e-02 -1.90466717e-02 -1.24641526e-02 3.20683345e-02
      1.17916660e-02 -1.01513769e-02 -9.50310146e-04 -1.03488844e-02
      -1.21806310e-02 -7.33999722e-03 -1.85503047e-02 -8.10091477e-03
      8.42163619e-03 6.46321382e-03 6.50360854e-03 2.22822260e-02
      6.15740288e-03 -8.87845643e-03 1.73264015e-02 -1.00495561e-03
      4.96114884e-03 1.27563421e-02 1.43873701e-02 2.69511854e-03
      9.03304480e-03 -2.62164548e-02 -2.32185069e-02 4.21190125e-05
      -6.28433051e-03 2.31486070e-03 1.09811770e-02 1.40135540e-02
      -3.46929370e-03 -7.80845154e-03 -9.41608287e-03 -3.20103485e-03
      -2.65415758e-02 -3.45034921e-03 7.73664471e-03 7.90878013e-03
      1.77430529e-02 8.90859310e-03 -8.90489202e-03 -1.70020014e-02
      -1.66394212e-03 -2.47286856e-02 8.20575375e-03 -3.58256453e-04
      9.82852839e-03 3.93205434e-02 5.03136683e-03 1.32748624e-02
      -1.41084101e-02 4.07042168e-03 -2.75317617e-02 -8.60098004e-03
      6.52542384e-03 -4.74301726e-03 2.38835048e-02 2.61045508e-02
      -2.52454798e-03 -1.95602272e-02 -1.64300837e-02 -2.26377733e-02
      7.81220663e-03 5.03530167e-03 6.57340512e-03 1.27636828e-02
      9.66342818e-03 -2.23889272e-03 1.13910474e-02 5.95685933e-03
      -2.76945289e-02 -3.59940389e-03 1.33826928e-02 -1.07745612e-02
      1.83417797e-02 -1.25995502e-02 -8.71213735e-04 1.09341079e-02
      3.44467983e-02 1.35526313e-02 1.47417309e-02 -1.55498541e-03
      -9.35324840e-03 -9.02996678e-03 6.70348946e-03 1.18622920e-02
      -5.75257652e-03 -6.27707923e-03 -1.44028775e-02 1.52062410e-02
      1.47731742e-02 1.42329577e-02 1.10692577e-02 -2.02998854e-02
      -1.10164275e-02 -3.10061593e-03 3.51519249e-02 2.23605279e-02
      3.44038047e-02 6.68042898e-03 -2.10115816e-02 -2.55965032e-02
      1.11535117e-02 3.00444243e-03 1.41952401e-02 1.55415321e-02
      2.68647389e-04 -1.95367485e-02 -1.28681248e-03 -1.21440040e-02
      -9.14471038e-03 2.15477776e-02 -2.71367258e-03 1.95605354e-03
      1.64240357e-02 1.67327328e-03 -1.61227100e-02 1.26914475e-02
      1.77521557e-02 9.14015900e-03 3.69983651e-02 6.79621985e-03
      1.85650103e-02 2.98032444e-02 6.87639229e-03 -2.66503990e-02
      -4.84729419e-03 -1.27907442e-02 -8.78133625e-03 3.54919881e-02
      9.22594313e-03 1.23371547e-02 1.93048511e-02 1.82810258e-02
      -2.00399924e-02 -1.66282356e-02 2.71670222e-02 4.09109779e-02
      -2.02030204e-02 -1.11463862e-02 -4.64890664e-03 1.25882579e-02
      5.91529626e-03 -1.53436000e-02 -1.09492079e-03 1.93708111e-02
      -3.06815002e-03 -2.55539697e-02 -2.33348757e-02 -1.56267011e-03
      2.06124019e-02 1.99118722e-02 -1.82857309e-02 -2.64147692e-03
      4.46277559e-02 3.06783356e-02 9.15792864e-03 -2.20874604e-02
      -2.20247637e-03 1.31935598e-02 -5.44424809e-04 -2.14587804e-02
      -2.17209011e-02 3.67588960e-02 4.61234301e-02 3.17236781e-02
      -2.04614569e-02 1.04537734e-03 1.29263019e-02 2.18905881e-03
      -1.59476865e-02 -1.46654183e-02 4.72866856e-02 7.44150877e-02
      -3.16735059e-02 -3.85104194e-02 -1.02736168e-02 1.59886864e-03
      2.01194757e-03 -1.48847215e-02 -2.20443569e-02 1.44281955e-02
      2.75651589e-02 6.41506026e-03 -4.50165235e-02 -3.07271518e-02
      2.18954124e-03 9.06623434e-03 -7.18412036e-03 -1.03791710e-02
      1.20790466e-03 4.46478613e-02 4.59675565e-02 -2.21213643e-02
      -8.05437658e-03 -4.07385547e-03 -9.23381071e-04 -9.95221268e-03
      -2.83871368e-02 3.80572700e-03 6.03272505e-02 1.53592248e-02
      -2.36954726e-02 -4.37128963e-03 1.40834181e-02 1.96765643e-02
      -5.23527991e-03 -1.55470595e-02 -1.84351429e-02 4.53643166e-02
      -7.44257914e-03 -1.80126876e-02 -2.03331802e-02 -4.83894115e-03
      1.71659477e-02 -1.06220450e-02 -9.12814215e-03 -1.02239521e-02
      3.41898017e-03 -3.05507276e-02 -3.07671782e-02 -1.99220125e-02
      5.44817336e-02 4.85480875e-02 -1.22834777e-03 -1.74378119e-02
      -1.30774695e-02 -1.31967831e-02 1.14829037e-02 -2.58751903e-02
      4.52892948e-03 1.92583073e-02 7.99250696e-03 -1.52673228e-02
      -1.00638298e-02 -1.78415459e-02 6.33885851e-03 -7.83177465e-03
      -5.88811794e-03 5.32778772e-03 3.22859883e-02 9.93852317e-03
      -1.80222131e-02 2.58853263e-03 -8.74763355e-03 -5.07703982e-04
      -2.83761676e-02 -2.33869180e-02 -1.99293327e-02 5.42396642e-02
      6.78792521e-02 6.42241910e-03 -8.74193851e-03 -4.27483255e-03
      -2.11737044e-02 -2.83181611e-02 -1.07183540e-02 -2.98363529e-02
      6.21552998e-03 4.49151248e-02 3.15139517e-02 8.25579278e-03
      4.65695886e-03 -2.49144360e-02 -1.58378668e-02 -3.42403213e-03
      1.25533622e-02 4.61475514e-02 2.34421343e-02 5.56061650e-03
      3.68028204e-03 7.89402984e-03 -1.68069266e-02 -1.54976016e-02
      1.07345320e-02 -2.66140117e-03 1.97056308e-02 2.60480829e-02
      1.80478189e-02 1.30233830e-02 8.49294756e-03 -6.51867734e-03
      -1.28386337e-02 -8.42810422e-03 -3.10195796e-02 -2.40947362e-02
      3.11892089e-02 4.05392423e-02 1.58398151e-02 2.54840106e-02
      -2.31275447e-02 5.72270714e-03 5.98431472e-03 6.78073755e-03
      -1.35305654e-02 2.47036070e-02 2.43843831e-02 2.51374897e-02
      2.93692295e-02 -6.20490592e-03 -2.10257284e-02 1.85883109e-04
      -2.43752971e-02 -1.96912270e-02 1.39996884e-02 3.88960689e-02
      1.33934831e-02 1.49945850e-02 -1.52345980e-02 -1.15606037e-03
      3.61423776e-03 -1.20044136e-02 -2.61764117e-02 9.89353936e-03
      2.01174561e-02 3.42201032e-02 3.45336311e-02 2.16533374e-02
      2.49479767e-02 1.56839043e-02 -7.01808603e-04 -1.36640593e-02
      9.37444065e-03 -4.91085055e-04 -1.48076925e-03 -1.37574431e-02
      -8.51520963e-05 3.58509086e-02 1.59777142e-02 -1.75665449e-02
      -2.08232403e-02 -1.44467894e-02 -3.31594585e-03 -7.68186059e-03
      -2.26780418e-02 -1.95411223e-04 3.12037878e-02 1.15374960e-02
      -7.91976042e-03 -1.21196443e-02 -3.78001574e-03 -7.28478376e-03
      -3.14005208e-03 -8.31248146e-03 1.39071327e-02 3.69951539e-02
      1.31013226e-02 -3.23141553e-02 -2.15513855e-02 -5.31578483e-03
      -3.84331355e-03 -1.43158333e-02 -3.30359265e-02 2.71871202e-02
      2.59755775e-02 1.13444766e-02 -1.61749013e-02 -1.96703766e-02
      -2.45014783e-02 -1.33762546e-02 -5.48254466e-03 -1.06612686e-02
      9.64867510e-03 2.33419128e-02 1.35907074e-02 -1.04755685e-02
      -2.10207812e-02 -3.32407504e-02 -1.89462546e-02 -4.56546550e-04
      7.22343242e-03 9.38892178e-03 4.36808914e-02 4.94864257e-03
      -3.46702337e-02 -2.47121416e-02 -1.17093679e-02 -7.82885030e-03
      -5.94480336e-03 -3.55869764e-03 3.99048179e-02 2.06636526e-02
      1.65010802e-02 -2.42950954e-02 -2.27758903e-02 -1.98134631e-02
      4.49775631e-04 1.85733400e-02 2.60657147e-02 3.95118482e-02
      -1.27160503e-03 1.07935967e-03 -6.28859736e-03 -1.34051200e-02
      -2.62829624e-02 5.37639624e-03 2.34706476e-02 2.02038623e-02
      -5.93341561e-03 -1.57985110e-02 -1.19162407e-02 -1.94493793e-02
      -3.38522438e-03 -2.89901835e-03 3.21503058e-02 3.11631504e-02
      -5.98997576e-03 -2.28179619e-02 1.54289957e-02 1.30183692e-03
      -1.47693641e-02 -2.16751285e-02 -2.39612758e-02 2.43956503e-02
      6.46807626e-02 3.68837975e-02 1.25277145e-02 -1.62291136e-02
      -5.67614520e-03 -1.75359957e-02 -3.75851840e-02 -9.37505718e-03
      4.11913581e-02 4.61306572e-02 2.77674813e-02 -2.72430182e-02
      1.85354874e-02 1.36132669e-02 1.22241713e-02 2.38945875e-02
      -5.24972286e-03 -2.32991893e-02 -6.40956359e-03 -8.32922943e-03
      -1.30095063e-02 3.41273211e-02 1.76952109e-02 3.88406613e-03
      1.53621528e-02 1.01618022e-02 -1.60950087e-02 -2.19647139e-02
      9.18071833e-04 1.01194642e-02 1.07919415e-02 2.61120275e-02
      1.42638115e-02 2.64265742e-02 1.18572433e-02 1.18129430e-02
      -1.87208434e-03 -1.18774045e-02 -2.04208270e-02 3.25418226e-02
      2.39966344e-02 1.64739303e-02 2.03389172e-02 7.04185991e-03
      7.47325085e-03 -9.13683232e-03 3.33601085e-04 3.92308831e-03
      4.22821520e-03 -2.28563808e-02 -4.26924648e-03 1.99618023e-02
      3.59219173e-03 -1.06825866e-02 -2.76678894e-02 3.52974888e-03
      2.02352237e-02 3.69181260e-02 -9.09213722e-03 -2.67412839e-03
      2.15120856e-02 4.81029553e-03 -8.37688800e-03 -3.26533988e-02
      1.20006257e-03 4.84128259e-02 4.42225533e-03 -1.45605160e-02
      -2.13810406e-03 2.83109341e-02 7.98151549e-03 1.02198985e-03
      -3.05055571e-03 1.33346058e-02 1.45145347e-02 3.71749625e-02
      -1.03230672e-02 -6.99448679e-03 3.31327803e-02 1.17889112e-02
      2.57884618e-03 -1.80596821e-02 7.46547990e-03 3.54963541e-02
      4.94464487e-02 -1.33293401e-02 -1.35512175e-02 -2.77947378e-03
      -1.57238729e-03 -1.93276140e-03 -1.94483511e-02 -1.76771022e-02
      4.77777421e-02 1.98957454e-02 -1.62185598e-02 2.90439720e-03
      9.45553929e-03 -2.93665309e-03 -5.42096561e-03 -1.48334615e-02
      -3.37824114e-02 1.42035037e-02 4.75473665e-02 -1.60564855e-02
      -1.43135935e-02 3.56197543e-03 -8.79769796e-04 -3.53729585e-04
      -7.38292653e-03 -2.27475390e-02 2.90711801e-02 3.47339399e-02
      -6.71709096e-03 4.17524192e-04 -8.07457883e-03 -7.41589582e-03
      -1.19976122e-02 -1.99673101e-02 -3.91768068e-02 9.18763597e-03
      2.50301305e-02 1.33737572e-03 1.30972825e-02 2.44525988e-02
      -1.21211912e-03 -1.61035918e-02 -1.49036478e-02 -1.96133032e-02
      -7.94333965e-03 1.12458784e-02 -4.49015480e-03 8.58982932e-03
      2.57921666e-02 -1.59095358e-02 -1.98747274e-02 -9.85476468e-03
      -4.54683183e-03 -3.99998063e-03 2.61207633e-02 -1.11545129e-02
      9.01905261e-03 2.44238041e-03 -1.39540397e-02 -1.47014325e-02
      -2.99316254e-02 -2.41841879e-02 6.87690685e-03 5.38709685e-02
      -2.37702429e-02 4.95949574e-03 -3.27001954e-03 -2.75826007e-02
      -1.60426367e-02 -4.52242605e-03 -9.67173092e-03 3.34403627e-02
      9.44313221e-03 1.42196612e-02 1.49667114e-02 1.78310759e-02
      -2.08807364e-02 -9.38472338e-03 7.74244720e-04 6.40335819e-03
      -7.18550291e-03 1.40621318e-02 1.53543744e-02 -7.11337617e-03
      1.16555728e-02 -9.96988360e-03 2.09397427e-03 -2.39370414e-03
      1.67729822e-03 -1.93558373e-02 6.14192672e-02 -1.41754542e-02
      3.65526603e-06 -1.11553556e-04 -1.57782547e-02 -1.78045258e-02
      -1.43753998e-02 -2.06864998e-02 3.88690270e-02 4.25858572e-02
      5.88639360e-03 -4.63320781e-03 -8.11722479e-04 -6.09157886e-03
      -1.51941059e-02 -6.53972337e-03 -2.76448708e-02 9.42260399e-03
      -2.05101222e-02 3.99540551e-03 -1.17545500e-02 -6.28119428e-03
      -5.21207461e-03 1.26417298e-02 1.57892909e-02 9.03071370e-03
      -4.57823602e-03 -1.13447569e-02 8.30076169e-03 -7.40019511e-03
      -8.97563342e-03 -2.47226586e-03 1.42204892e-02 1.81560777e-02
      4.52533774e-02 2.26824675e-02 5.70084108e-03 1.20313335e-02
      -7.93572329e-03 -1.76015515e-02 -1.50261195e-02 -5.05998079e-03
      4.44619870e-03 9.83295962e-04 1.12683680e-02 5.05411765e-03
      5.71707124e-03 -6.01974409e-03 -4.83518559e-03 -4.95961774e-03
      -2.58401129e-03 -1.42922029e-02 4.24498052e-04 1.26353707e-02
      2.28069257e-02 1.31668907e-03 -6.27139490e-03 -3.61482892e-03
      -1.69650046e-03 -1.34857942e-03 -1.89254549e-03 -1.37305511e-02
      8.55829380e-03 2.70624161e-02 -2.23506871e-03 -2.77047846e-02
      -1.42834093e-02 -2.12626648e-03 -2.02063797e-03 -4.61698091e-03
      -2.40624435e-02 1.44316508e-02 1.64645985e-02 3.97902820e-03
      -5.12960320e-03 -7.87101395e-04 -1.70567003e-03 -8.75663536e-04
      -3.09407827e-03 -2.88045909e-02 2.85364464e-02 2.27264743e-02
      3.04225972e-03 -1.09472657e-02 -1.05308164e-02 -4.33380762e-03
      -4.56438866e-03 -9.83222108e-03 -2.81698834e-02 1.12769902e-02
      2.93858666e-02 -8.62540491e-03 -2.58671753e-02 -1.60721708e-02
      -5.85785741e-03 -3.77180916e-03 1.42914068e-03 -5.49586909e-03
      1.82335190e-02 1.92388222e-02 -2.89258151e-03 -1.70521699e-02
      -8.82826280e-04 -1.00404862e-02 2.08998169e-03 2.76888218e-02
      1.10511174e-02 2.12235469e-02 2.45401151e-02 -9.70342779e-04
      -9.46738385e-03 -2.85353302e-03 -2.33164686e-03 -1.13929585e-02
      -6.83714636e-03 -1.83101203e-02 5.33303339e-03 1.93881579e-02
      1.53067335e-02 -1.51579815e-03 7.70747755e-03 8.33180267e-04
      -1.64528452e-02 3.64685524e-03 -2.48794332e-02 -4.57707653e-03
      2.39486294e-03 -2.71225814e-03 -1.79152079e-02 -7.13607157e-03
      -1.63773112e-02 3.90292481e-02 3.01584769e-02 8.16847011e-03
      -1.24309175e-02 -1.65403821e-02 -5.87861659e-03 -2.10805926e-02
      -1.18466159e-02 -2.28613336e-03 4.81488742e-02 2.39429083e-02
      -1.33568654e-03 -1.81287695e-02 9.80927050e-03 1.21626821e-04
      3.07790819e-03 1.87525116e-02 1.76929682e-02 1.62386037e-02
      2.04135496e-02 -1.95236821e-02 -2.01439988e-02 -8.21118802e-03
      -1.71592515e-02 -1.27236601e-02 2.71160658e-02 1.78043749e-02
      2.33612694e-02 1.04504246e-02 -1.12463832e-02 -2.23427452e-02
      -1.60332897e-03 8.43218435e-03 4.23191907e-03 1.13700684e-02
      3.03066149e-03 2.72001084e-02 1.75174512e-03 -1.89682643e-03
      -2.10215040e-02 2.85219867e-03 9.06392746e-03 7.34357722e-03
      5.59103396e-03 -5.05681522e-03 1.89362895e-02 -2.13026139e-03
      9.61674005e-03 4.14630119e-03 -2.31698877e-03 -1.07942405e-03
      1.78125373e-03 -2.49254191e-03 7.07357936e-03 2.47102100e-02
      1.47166168e-02 1.54609727e-02 -3.01786303e-03 8.06470402e-03
      8.95112939e-03 6.28205901e-03 -4.89967410e-03 -1.46648344e-02
      1.26056038e-02 5.81347896e-03 1.40453205e-02 7.73886568e-05
      -6.52763294e-03 -3.54615902e-03 -1.36185717e-03 1.53366784e-02
      -2.63195339e-04 2.78190523e-03 -3.55016859e-03 1.12790326e-02
      2.26959400e-03 3.43097672e-02 -1.07797710e-02 -9.87473596e-03
      2.53715441e-02 9.54338908e-03 6.19251374e-03 -7.72424694e-03
      7.23813474e-03 2.89656520e-02 4.09414666e-03 5.66617865e-03
      4.36503813e-03 1.51635706e-03 -3.42650875e-03 5.90403471e-03
      -5.94632188e-03 1.14224164e-03 -1.52074068e-03 3.94186974e-02
      -1.29915611e-03 -2.87016388e-03 3.78300785e-03 -5.71386481e-04
      -1.35202310e-03 -1.27615808e-02 -1.13855610e-02 -3.48086492e-03
      3.83037366e-02 -1.01351952e-02 -6.46669883e-03 1.55601674e-03
      -8.79937375e-04 -3.57597950e-03 -3.79228825e-03 -1.92935169e-02
      1.66890677e-02 3.87914553e-02 -2.52003893e-02 -7.69757153e-03
      -2.94129294e-03 -3.85569595e-03 -8.11389554e-03 -9.65961255e-03
      -1.59998182e-02 1.98541917e-02 3.75922322e-02 -1.04729095e-02
      -6.59429282e-03 -1.50936563e-03 -9.19791171e-04 -3.20390682e-03
      -5.10487566e-03 -2.92189158e-02 6.52237097e-03 2.60975510e-02
      -1.55171072e-02 -1.20087015e-02 -1.54223281e-03 -1.44177710e-03
      -4.84891282e-03 -5.64468000e-03 -1.94129422e-02 4.71115857e-03
      1.81822702e-02 -3.62047702e-02 -6.57027075e-03 -7.23476848e-03
      -3.35509656e-03 -2.09312397e-03 -5.37301600e-03 -7.68054463e-03
      2.46910341e-02 5.12185954e-02 -4.92933616e-02 -1.02368388e-02
      -6.24258723e-03 -1.22253094e-02 -6.02462841e-03 -8.48397613e-03
      -3.92433163e-03 3.97678241e-02 2.62123384e-02 -3.82390171e-02
      -9.23825894e-03 -4.36393358e-03 -1.12352916e-03 -4.19543125e-04
      -2.01745657e-03 -7.69849354e-03 1.49545278e-02 1.66794509e-02
      -3.50381099e-02 -7.43962405e-03 -5.94757497e-03 -6.61992468e-03
      -2.74075032e-03 -1.39354059e-04 -6.00580219e-03 -1.56768993e-03
      5.33838794e-02 -3.74288969e-02 -2.11790316e-02 -3.44421435e-03
      -6.63692271e-03 -1.05445692e-02 -1.37092778e-02 -1.15640135e-02
      2.38937866e-02 4.41275984e-02 -2.26340536e-02 -2.02398933e-02
      -1.45692090e-02 -4.59595025e-03 -8.16441420e-03 -1.60320066e-02
      -3.94256450e-02 1.95806809e-02 2.88608130e-02 -3.32752205e-02
      -1.18768746e-02 -2.49948492e-03 -7.55217904e-03 -6.57797977e-03
      -4.21437807e-03 -6.68704137e-03 1.30791152e-02 2.76169199e-02
      -2.19960753e-02 -1.70677230e-02 -1.14921788e-02 -9.68451146e-03
      -8.89079459e-03 -1.30904084e-02 -2.23282073e-02 3.21641080e-02
      1.65199991e-02 -4.95878095e-03 -1.19658690e-02 -1.88862663e-02
      -4.81938804e-03 -5.55831240e-03 -9.11738351e-03 -1.39178671e-02
      1.96590107e-02 -6.45464024e-05 -1.31030502e-02 -9.58827045e-03
      -5.99630224e-03 -3.93670145e-03 -5.31561440e-03 -1.02375997e-02
      -1.59919560e-02 3.47409099e-02 2.92749256e-02 -9.06862505e-03
      -8.66479520e-03 -1.20177977e-02 -4.62844875e-03 -1.28367962e-02
      -1.25108054e-02 -2.99565140e-02 3.01915128e-02 2.03300007e-02
      -2.89698932e-02 -8.78017303e-03 -6.45383028e-03 -1.04022380e-02
      -1.29825072e-02 -1.54903186e-02 -4.05887701e-02 2.29101405e-02
      1.31788766e-02 -5.57575794e-03 -4.79675317e-03 -3.35027929e-04
      -2.06398056e-03 -5.25762967e-04 -2.48400308e-03 -2.22916156e-02
      2.00313348e-02 4.47193719e-02 -1.18961725e-02 -1.11297052e-02
      -4.19880124e-03 -3.05966591e-03 -3.19403131e-03 -1.22401463e-02
      -2.23556925e-02 1.89830130e-03 1.81897283e-02 -2.06661727e-02
      -7.54216546e-03 -2.07395223e-03 -4.63690842e-03 -3.44973546e-03
      -1.48927020e-02 -2.72386111e-02 1.67256612e-02 2.72141807e-02
      -1.89034771e-02 -1.29991574e-02 -3.06129735e-03 -4.62167105e-03
      -3.25455260e-03 -2.11020485e-02 -1.96416117e-02 9.41066723e-03
      3.18013951e-02 -3.73117300e-03 -1.17113302e-02 -1.65815011e-03
      -1.84090249e-03 -8.30719620e-03 -7.31635652e-03 -1.54878097e-02
      2.64745136e-03 3.52985896e-02 1.81597639e-02 -1.27762752e-02
      9.21095815e-03 7.80260889e-03 -1.67053565e-02 -1.17417909e-02
      -3.48940641e-02 -1.59632172e-02 2.81015206e-02 -1.14389444e-02
      -1.33109763e-02 1.85664263e-04 -2.76498706e-03 -1.88390573e-03
      -7.00859027e-03 -2.20315363e-02 1.13864094e-02 1.24738580e-02
      2.80948449e-03 -1.41536165e-02 -6.02236809e-03 2.47669732e-03
      -1.36871543e-03 -1.29612358e-02 -3.01811583e-02 -8.57265946e-03
      1.63800102e-02 6.65118545e-03 1.25112720e-02 2.31125914e-02
      1.29726669e-02 -4.84437076e-03 -4.26144386e-03 -1.46904355e-02
      -1.01382723e-02 -2.01114407e-03 -1.79779287e-02 1.51195424e-02
      2.14264616e-02 1.85297560e-02 -2.95902183e-03 9.12336051e-04
      -6.14456786e-03 -1.47827715e-02 1.75993051e-02 2.21192162e-03
      1.15535473e-02 1.72394738e-02 -1.06353806e-02 -5.19147050e-03
      -1.14467181e-02 -1.01618711e-02 -3.97846010e-03 -8.58732313e-03
      -1.02407122e-02 2.18991991e-02 1.09561319e-02 1.32866099e-03
      -1.20977936e-02 -2.80904491e-03 -9.90698696e-04 -5.87856397e-03
      5.51908743e-03 1.07665360e-03 5.78340050e-03 -6.49199169e-03
      -1.14401691e-02 2.76636332e-03 7.22374162e-03 1.33138746e-02
      8.46452452e-03 3.23050693e-02 1.47532858e-02 6.86234934e-03
      -1.68167297e-02 -1.36741018e-02 -2.04467773e-03 -4.15726379e-03
      1.00340918e-02 4.88323485e-03 2.01730225e-02 3.88073619e-03
      5.95920300e-03 -4.69061034e-03 -1.65969320e-02 -1.57532766e-02
      8.24532565e-03 5.72786015e-03 1.37286615e-02 3.98910940e-02
      3.53372470e-02 1.37085887e-02 -1.55804893e-02 1.02714738e-02
      -1.34867048e-02 -3.56147857e-03 -2.36622095e-02 -5.29672159e-03
      2.04084739e-02 1.13623440e-02 5.01134945e-03 -5.89439552e-03
      -4.97686304e-03 2.59722397e-03 -1.76922115e-03 -8.13520420e-03
      -5.79134561e-03 2.47225557e-02 1.73789449e-02 4.60592710e-04
      -4.43948153e-03 -2.60686968e-03 -4.93056001e-03 -1.21409083e-02
      -3.11490577e-02 -3.47682554e-03 3.17270495e-02 1.43726049e-02
      3.80905648e-03 -1.03832092e-02 3.07659502e-03 -1.02304337e-04
      1.26585655e-03 -5.93433762e-03 -2.48098709e-02 3.27133872e-02
      3.28469053e-02 4.28159675e-03 -6.76812092e-03 1.18995914e-02
      -3.13521503e-03 -8.75186117e-04 -1.72227733e-02 -9.51691810e-03
      3.79360802e-02 2.97911069e-03 -5.44558093e-03 -4.39313380e-03
      -2.61399732e-03 -2.54955259e-03 -5.18406415e-03 -2.46470254e-02
      1.13334749e-02 1.19480761e-02 9.90861468e-03 -7.48886913e-03
      -2.34480412e-03 -2.98491842e-03 -1.73839857e-03 -4.86112572e-03
      -2.10476611e-02 -9.06348170e-04 1.15009090e-02 8.28757137e-03
      -1.06344826e-03 -2.30239518e-03 -1.25966629e-03 -1.35777984e-03
      -2.92622810e-03 6.70793588e-06 6.91442750e-03 8.34097061e-03
      1.34404320e-02 -4.07026475e-03 -9.01281659e-04 7.91463722e-03
      -7.43295474e-04 -3.82037461e-03 -1.47173868e-03 3.67991999e-03
      2.05890443e-02 -1.10770054e-02 -4.93353978e-03 -2.64442782e-03
      -2.56314495e-04 1.73916749e-04 -2.15031882e-03 -4.70353477e-03
      -3.57374054e-04 1.03574421e-03 7.20300060e-03 -1.10710145e-03
      -6.18200842e-03 -1.77096261e-03 -2.73527787e-03 -1.17360929e-03
      -7.73704052e-03 -7.57160643e-03 -2.31041503e-03 5.20315953e-04
      -1.22759480e-03 -1.06369285e-03 1.23167960e-02 1.10637711e-03
      -1.69490220e-03 1.66656927e-03 7.57503789e-03 4.86515788e-03
      2.96276081e-02 -4.97436151e-04 -2.23496743e-03 1.22244121e-03
      -3.51901795e-03 -2.90000858e-03 -6.72960142e-03 -1.75827052e-02
      2.16660742e-02 1.37169496e-03 -7.40758842e-03 -4.72545205e-03
      -1.13019403e-02 -5.50443074e-03 -1.89068972e-03 -7.75344204e-03
      8.33558559e-04 2.89063677e-02 -1.42443972e-02 -9.47557390e-03
      -5.83412359e-03 -1.18085882e-02 -8.02645274e-03 -4.39209025e-03
      -1.14119500e-02 2.53724437e-02 3.55213359e-02 1.28163928e-02
      -8.77259392e-03 -8.98878369e-03 -8.33786465e-03 -5.66588622e-03
      -3.50878900e-03 -1.08614545e-02 -1.27877686e-02 3.65076102e-02
      3.50740436e-03 -6.65523112e-03 -7.59989768e-03 -3.02965380e-03
      -9.63232294e-03 -1.16321873e-02 -9.03059263e-03 4.04788321e-03
      2.31813677e-02 -7.32031837e-03 -1.11943926e-03 -3.38754733e-03
      -3.90950171e-03 -5.74133219e-03 -4.11517639e-03 -1.03392638e-02
      2.98981033e-02 1.42356548e-02 -1.86053310e-02 -4.95168101e-03
      -8.26949440e-03 -7.77867157e-03 -4.86525055e-03 -1.02953482e-02
      -1.60155836e-02 2.52417754e-02 1.08324992e-03 -1.67928881e-03
      2.53447169e-03 -2.08274112e-03 3.94974183e-03 -7.46992044e-03
      -2.32486171e-03 -1.21830339e-02 -1.91777930e-04 -1.53042367e-02
      8.77601618e-04 -3.58398911e-03 -1.07206749e-02 -1.20504433e-02
      -3.80314770e-03 -1.44586514e-03 2.98858766e-04 1.42251635e-02
      2.86267176e-02 -9.35053267e-03 -6.01220969e-03 -2.25630216e-03
      -1.89393398e-03 -3.27257719e-03 -1.01385051e-02 -1.24432277e-02
      2.62637045e-02 3.27966288e-02 -4.76599392e-03 -7.98704010e-03
      -2.13030842e-03 -2.21958174e-03 -1.90130225e-03 -1.19768847e-02
      -9.01670940e-03 2.25558691e-02 4.66330349e-03 3.05484910e-03
      -2.79270555e-03 -3.24857584e-03 -1.53329801e-02 -8.33824510e-04
      -4.78931889e-03 -4.24020737e-03 -3.67758586e-03 5.26181050e-03
      9.27144010e-03 -1.43399043e-03 -2.31318944e-03 -7.89574534e-03
      -4.69593157e-04 -1.87622313e-03 7.33511802e-03 2.00350024e-03
      2.14409214e-02 -3.41409864e-03 -4.87144943e-03 -2.36707288e-04
      -3.62723693e-03 1.08580047e-03 -2.77581807e-06 -3.25134560e-03
      1.74408183e-02 6.12592138e-03 8.32966622e-03 1.19049996e-02
      3.79151898e-03 -4.92939819e-03 3.33439955e-03 1.69616472e-03
      1.47972512e-03 1.15766155e-03 -2.98568308e-02 2.02035299e-03
      4.47570067e-03 -1.15368830e-03 -1.18689574e-02 -1.87894283e-03
      1.49980350e-03 1.38040129e-02 -2.34563183e-03 -6.13097940e-03
      8.05777963e-03 7.99234584e-03 -9.65032727e-04 -1.40890777e-02
      -4.55778558e-03 1.55680813e-04 1.93964876e-02 1.19779364e-03
      2.73972168e-03 2.99684377e-03 2.82816961e-02 1.32886637e-02
      -2.32623965e-02 -2.00713216e-03 -3.27187008e-04 1.98693201e-03
      4.98639711e-04 -1.47595396e-02 -2.61112815e-03 2.24417821e-02
      1.68524031e-02 1.12566596e-03 6.52831141e-03 4.78519453e-03
      2.90583982e-03 -2.57528271e-04 -3.08472489e-04 -6.63218787e-03
      8.65322072e-03 -2.83291447e-03 -1.01178838e-02 -7.12705823e-03
      4.45542624e-03 1.37068506e-03 -8.34403466e-03 -2.59316899e-02
      -7.55966362e-03 -6.13642100e-04 -7.00479466e-03 2.37347540e-02
      1.08089186e-02 4.49708523e-03 5.91797521e-03 -1.19008152e-02</_></support_vectors>
  <decision_functions>
    <_>
      <sv_count>1</sv_count>
      <rho>2.3935301031685774e+00</rho>
      <alpha>
        1.</alpha>
      <index>
        0</index></_></decision_functions></my_svm>
</opencv_storage>
